[{"ecutrho":100,"k_density":0.1,"ecutwfc":20,"n_iterations":34,"time":591145,"converged":true,"accuracy":6.4e-10,"fermi":10.9844,"total_energy":-286.90768829},{"ecutrho":100,"k_density":0.5,"ecutwfc":20,"n_iterations":16,"time":4074,"converged":true,"accuracy":1.9e-10,"fermi":10.9755,"total_energy":-286.905330685},{"ecutrho":100,"k_density":0.25,"ecutwfc":20,"n_iterations":40,"time":52103,"converged":true,"accuracy":5.6e-10,"fermi":10.9683,"total_energy":-286.907583615},{"ecutrho":100,"k_density":0.16666666666666666,"ecutwfc":20,"n_iterations":51,"time":215076,"converged":true,"accuracy":5.2e-10,"fermi":10.9784,"total_energy":-286.9077176},{"ecutrho":100,"k_density":0.125,"ecutwfc":20,"n_iterations":35,"time":348173,"converged":true,"accuracy":8.3e-10,"fermi":10.9853,"total_energy":-286.907675305},{"ecutrho":140,"k_density":0.1,"ecutwfc":20,"n_iterations":34,"time":591086,"converged":true,"accuracy":9.3e-10,"fermi":10.9845,"total_energy":-286.907674255},{"ecutrho":140,"k_density":0.5,"ecutwfc":20,"n_iterations":16,"time":4064,"converged":true,"accuracy":1.1e-10,"fermi":10.9757,"total_energy":-286.905316625},{"ecutrho":140,"k_density":0.25,"ecutwfc":20,"n_iterations":56,"time":64099,"converged":true,"accuracy":8.3e-10,"fermi":10.9683,"total_energy":-286.90756966},{"ecutrho":140,"k_density":0.16666666666666666,"ecutwfc":20,"n_iterations":30,"time":110092,"converged":true,"accuracy":5.5e-10,"fermi":10.9786,"total_energy":-286.907702905},{"ecutrho":140,"k_density":0.125,"ecutwfc":20,"n_iterations":29,"time":297108,"converged":true,"accuracy":3.1e-10,"fermi":10.9853,"total_energy":-286.907661265},{"ecutrho":180,"k_density":0.1,"ecutwfc":20,"n_iterations":34,"time":544055,"converged":true,"accuracy":3.1e-10,"fermi":10.9844,"total_energy":-286.907675295},{"ecutrho":180,"k_density":0.5,"ecutwfc":20,"n_iterations":16,"time":4068,"converged":true,"accuracy":5.4e-10,"fermi":10.9757,"total_energy":-286.90531767},{"ecutrho":180,"k_density":0.25,"ecutwfc":20,"n_iterations":54,"time":65115,"converged":true,"accuracy":5.9e-10,"fermi":10.9683,"total_energy":-286.907570705},{"ecutrho":180,"k_density":0.16666666666666666,"ecutwfc":20,"n_iterations":28,"time":106112,"converged":true,"accuracy":9.0e-10,"fermi":10.9786,"total_energy":-286.907702645},{"ecutrho":180,"k_density":0.125,"ecutwfc":20,"n_iterations":34,"time":303178,"converged":true,"accuracy":3.5e-10,"fermi":10.9853,"total_energy":-286.907662285},{"ecutrho":220,"k_density":0.1,"ecutwfc":20,"n_iterations":31,"time":554118,"converged":true,"accuracy":6.5e-10,"fermi":10.9845,"total_energy":-286.90767777},{"ecutrho":220,"k_density":0.5,"ecutwfc":20,"n_iterations":16,"time":4077,"converged":true,"accuracy":5.7e-10,"fermi":10.9757,"total_energy":-286.905320185},{"ecutrho":220,"k_density":0.25,"ecutwfc":20,"n_iterations":33,"time":41111,"converged":true,"accuracy":8.4e-10,"fermi":10.9689,"total_energy":-286.90757098},{"ecutrho":220,"k_density":0.16666666666666666,"ecutwfc":20,"n_iterations":36,"time":115090,"converged":true,"accuracy":8.9e-11,"fermi":10.9784,"total_energy":-286.90770713},{"ecutrho":220,"k_density":0.125,"ecutwfc":20,"n_iterations":26,"time":259136,"converged":true,"accuracy":6.1e-10,"fermi":10.9853,"total_energy":-286.907664445},{"ecutrho":260,"k_density":0.1,"ecutwfc":20,"n_iterations":34,"time":515128,"converged":true,"accuracy":4.4e-10,"fermi":10.9843,"total_energy":-286.90767868},{"ecutrho":260,"k_density":0.5,"ecutwfc":20,"n_iterations":16,"time":4079,"converged":true,"accuracy":5.9e-10,"fermi":10.9757,"total_energy":-286.9053212},{"ecutrho":260,"k_density":0.25,"ecutwfc":20,"n_iterations":52,"time":59089,"converged":true,"accuracy":6.3e-10,"fermi":10.9684,"total_energy":-286.90757376},{"ecutrho":260,"k_density":0.16666666666666666,"ecutwfc":20,"n_iterations":36,"time":122082,"converged":true,"accuracy":8.6e-10,"fermi":10.9784,"total_energy":-286.90770814},{"ecutrho":260,"k_density":0.125,"ecutwfc":20,"n_iterations":30,"time":269083,"converged":true,"accuracy":4.5e-10,"fermi":10.9853,"total_energy":-286.907665785},{"ecutrho":300,"k_density":0.1,"ecutwfc":20,"n_iterations":34,"time":561080,"converged":true,"accuracy":3.8e-12,"fermi":10.9845,"total_energy":-286.907679445},{"ecutrho":300,"k_density":0.5,"ecutwfc":20,"n_iterations":16,"time":4088,"converged":true,"accuracy":5.7e-10,"fermi":10.9757,"total_energy":-286.905321835},{"ecutrho":300,"k_density":0.25,"ecutwfc":20,"n_iterations":45,"time":55079,"converged":true,"accuracy":6.7e-10,"fermi":10.9685,"total_energy":-286.90757435},{"ecutrho":300,"k_density":0.16666666666666666,"ecutwfc":20,"n_iterations":41,"time":150089,"converged":true,"accuracy":8.7e-10,"fermi":10.9784,"total_energy":-286.907708765},{"ecutrho":300,"k_density":0.125,"ecutwfc":20,"n_iterations":42,"time":373145,"converged":true,"accuracy":8.2e-10,"fermi":10.9853,"total_energy":-286.907666465},{"ecutrho":340,"k_density":0.1,"ecutwfc":20,"n_iterations":35,"time":607116,"converged":true,"accuracy":3.2e-10,"fermi":10.9844,"total_energy":-286.90767971},{"ecutrho":340,"k_density":0.5,"ecutwfc":20,"n_iterations":16,"time":4083,"converged":true,"accuracy":5.6e-10,"fermi":10.9757,"total_energy":-286.905322095},{"ecutrho":340,"k_density":0.25,"ecutwfc":20,"n_iterations":68,"time":79155,"converged":true,"accuracy":2.6e-10,"fermi":10.9684,"total_energy":-286.90757512},{"ecutrho":340,"k_density":0.16666666666666666,"ecutwfc":20,"n_iterations":31,"time":112095,"converged":true,"accuracy":2.1e-10,"fermi":10.9784,"total_energy":-286.907709025},{"ecutrho":340,"k_density":0.125,"ecutwfc":20,"n_iterations":40,"time":375167,"converged":true,"accuracy":2.6e-10,"fermi":10.9853,"total_energy":-286.90766673},{"ecutrho":380,"k_density":0.1,"ecutwfc":20,"n_iterations":32,"time":551110,"converged":true,"accuracy":2.6e-10,"fermi":10.9845,"total_energy":-286.907679945},{"ecutrho":380,"k_density":0.5,"ecutwfc":20,"n_iterations":16,"time":4098,"converged":true,"accuracy":5.6e-10,"fermi":10.9757,"total_energy":-286.90532234},{"ecutrho":380,"k_density":0.25,"ecutwfc":20,"n_iterations":37,"time":47126,"converged":true,"accuracy":6.2e-11,"fermi":10.9685,"total_energy":-286.90757471},{"ecutrho":380,"k_density":0.16666666666666666,"ecutwfc":20,"n_iterations":35,"time":127085,"converged":true,"accuracy":2.4e-10,"fermi":10.9784,"total_energy":-286.907709265},{"ecutrho":380,"k_density":0.125,"ecutwfc":20,"n_iterations":39,"time":308142,"converged":true,"accuracy":1.7e-10,"fermi":10.9853,"total_energy":-286.90766675},{"ecutrho":100,"k_density":0.1,"ecutwfc":25,"n_iterations":35,"time":646125,"converged":true,"accuracy":9.5e-10,"fermi":10.982,"total_energy":-286.90990299},{"ecutrho":100,"k_density":0.5,"ecutwfc":25,"n_iterations":17,"time":5043,"converged":true,"accuracy":5.9e-12,"fermi":10.9725,"total_energy":-286.90751529},{"ecutrho":100,"k_density":0.25,"ecutwfc":25,"n_iterations":46,"time":58098,"converged":true,"accuracy":2.5e-10,"fermi":10.9659,"total_energy":-286.909751055},{"ecutrho":100,"k_density":0.16666666666666666,"ecutwfc":25,"n_iterations":39,"time":149085,"converged":true,"accuracy":3.2e-10,"fermi":10.9761,"total_energy":-286.9099256},{"ecutrho":100,"k_density":0.125,"ecutwfc":25,"n_iterations":38,"time":359067,"converged":true,"accuracy":5.7e-10,"fermi":10.9828,"total_energy":-286.909880445},{"ecutrho":140,"k_density":0.1,"ecutwfc":25,"n_iterations":42,"time":716081,"converged":true,"accuracy":9.4e-10,"fermi":10.982,"total_energy":-286.909888855},{"ecutrho":140,"k_density":0.5,"ecutwfc":25,"n_iterations":17,"time":5042,"converged":true,"accuracy":2.1e-10,"fermi":10.9726,"total_energy":-286.90750106},{"ecutrho":140,"k_density":0.25,"ecutwfc":25,"n_iterations":48,"time":62145,"converged":true,"accuracy":3.7e-10,"fermi":10.9656,"total_energy":-286.90973835},{"ecutrho":140,"k_density":0.16666666666666666,"ecutwfc":25,"n_iterations":35,"time":136095,"converged":true,"accuracy":5.8e-10,"fermi":10.9763,"total_energy":-286.90991114},{"ecutrho":140,"k_density":0.125,"ecutwfc":25,"n_iterations":38,"time":412053,"converged":true,"accuracy":1.6e-10,"fermi":10.9829,"total_energy":-286.90986631},{"ecutrho":180,"k_density":0.1,"ecutwfc":25,"n_iterations":36,"time":641093,"converged":true,"accuracy":2.0e-10,"fermi":10.982,"total_energy":-286.90988983},{"ecutrho":180,"k_density":0.5,"ecutwfc":25,"n_iterations":17,"time":5060,"converged":true,"accuracy":1.0e-11,"fermi":10.9725,"total_energy":-286.90750206},{"ecutrho":180,"k_density":0.25,"ecutwfc":25,"n_iterations":40,"time":51109,"converged":true,"accuracy":4.9e-10,"fermi":10.9659,"total_energy":-286.90973828},{"ecutrho":180,"k_density":0.16666666666666666,"ecutwfc":25,"n_iterations":47,"time":166097,"converged":true,"accuracy":8.0e-10,"fermi":10.9762,"total_energy":-286.90991266},{"ecutrho":180,"k_density":0.125,"ecutwfc":25,"n_iterations":44,"time":516069,"converged":true,"accuracy":2.5e-10,"fermi":10.9829,"total_energy":-286.90986724},{"ecutrho":220,"k_density":0.1,"ecutwfc":25,"n_iterations":39,"time":830101,"converged":true,"accuracy":5.3e-10,"fermi":10.982,"total_energy":-286.90989236},{"ecutrho":220,"k_density":0.5,"ecutwfc":25,"n_iterations":17,"time":5062,"converged":true,"accuracy":4.2e-11,"fermi":10.9725,"total_energy":-286.907504555},{"ecutrho":220,"k_density":0.25,"ecutwfc":25,"n_iterations":43,"time":55120,"converged":true,"accuracy":2.3e-10,"fermi":10.9657,"total_energy":-286.909741875},{"ecutrho":220,"k_density":0.16666666666666666,"ecutwfc":25,"n_iterations":40,"time":159139,"converged":true,"accuracy":4.0e-10,"fermi":10.9761,"total_energy":-286.90991515},{"ecutrho":220,"k_density":0.125,"ecutwfc":25,"n_iterations":28,"time":319119,"converged":true,"accuracy":4.3e-10,"fermi":10.9829,"total_energy":-286.90986914},{"ecutrho":260,"k_density":0.1,"ecutwfc":25,"n_iterations":32,"time":678122,"converged":true,"accuracy":6.2e-10,"fermi":10.982,"total_energy":-286.90989336},{"ecutrho":260,"k_density":0.5,"ecutwfc":25,"n_iterations":17,"time":5064,"converged":true,"accuracy":5.1e-12,"fermi":10.9726,"total_energy":-286.907505545},{"ecutrho":260,"k_density":0.25,"ecutwfc":25,"n_iterations":43,"time":59149,"converged":true,"accuracy":8.8e-10,"fermi":10.9656,"total_energy":-286.909742805},{"ecutrho":260,"k_density":0.16666666666666666,"ecutwfc":25,"n_iterations":37,"time":161073,"converged":true,"accuracy":3.9e-10,"fermi":10.9762,"total_energy":-286.90991616},{"ecutrho":260,"k_density":0.125,"ecutwfc":25,"n_iterations":33,"time":362110,"converged":true,"accuracy":7.4e-10,"fermi":10.9829,"total_energy":-286.909870545},{"ecutrho":300,"k_density":0.1,"ecutwfc":25,"n_iterations":53,"time":1234120,"converged":true,"accuracy":6.9e-10,"fermi":10.982,"total_energy":-286.90989401},{"ecutrho":300,"k_density":0.5,"ecutwfc":25,"n_iterations":17,"time":5061,"converged":true,"accuracy":8.2e-12,"fermi":10.9725,"total_energy":-286.907506195},{"ecutrho":300,"k_density":0.25,"ecutwfc":25,"n_iterations":46,"time":56152,"converged":true,"accuracy":7.4e-10,"fermi":10.9657,"total_energy":-286.90974354},{"ecutrho":300,"k_density":0.16666666666666666,"ecutwfc":25,"n_iterations":55,"time":197155,"converged":true,"accuracy":7.8e-11,"fermi":10.9761,"total_energy":-286.9099168},{"ecutrho":300,"k_density":0.125,"ecutwfc":25,"n_iterations":47,"time":422063,"converged":true,"accuracy":3.3e-10,"fermi":10.9829,"total_energy":-286.909871415},{"ecutrho":340,"k_density":0.1,"ecutwfc":25,"n_iterations":35,"time":677137,"converged":true,"accuracy":8.5e-10,"fermi":10.9821,"total_energy":-286.909894055},{"ecutrho":340,"k_density":0.5,"ecutwfc":25,"n_iterations":17,"time":5062,"converged":true,"accuracy":3.8e-12,"fermi":10.9726,"total_energy":-286.90750646},{"ecutrho":340,"k_density":0.25,"ecutwfc":25,"n_iterations":52,"time":66093,"converged":true,"accuracy":2.9e-10,"fermi":10.9657,"total_energy":-286.90974381},{"ecutrho":340,"k_density":0.16666666666666666,"ecutwfc":25,"n_iterations":43,"time":171117,"converged":true,"accuracy":5.7e-11,"fermi":10.9761,"total_energy":-286.90991707},{"ecutrho":340,"k_density":0.125,"ecutwfc":25,"n_iterations":40,"time":359060,"converged":true,"accuracy":1.7e-10,"fermi":10.9828,"total_energy":-286.909871735},{"ecutrho":380,"k_density":0.1,"ecutwfc":25,"n_iterations":45,"time":759152,"converged":true,"accuracy":3.3e-10,"fermi":10.982,"total_energy":-286.909894525},{"ecutrho":380,"k_density":0.5,"ecutwfc":25,"n_iterations":17,"time":5079,"converged":true,"accuracy":3.8e-12,"fermi":10.9726,"total_energy":-286.90750672},{"ecutrho":380,"k_density":0.25,"ecutwfc":25,"n_iterations":56,"time":58141,"converged":true,"accuracy":1.8e-10,"fermi":10.9656,"total_energy":-286.90974406},{"ecutrho":380,"k_density":0.16666666666666666,"ecutwfc":25,"n_iterations":33,"time":143132,"converged":true,"accuracy":9.6e-10,"fermi":10.9763,"total_energy":-286.909916985},{"ecutrho":380,"k_density":0.125,"ecutwfc":25,"n_iterations":43,"time":390085,"converged":true,"accuracy":3.7e-10,"fermi":10.9828,"total_energy":-286.909871975},{"ecutrho":100,"k_density":0.1,"ecutwfc":30,"n_iterations":32,"time":586122,"converged":true,"accuracy":7.7e-10,"fermi":10.9802,"total_energy":-286.91106504},{"ecutrho":100,"k_density":0.5,"ecutwfc":30,"n_iterations":15,"time":4107,"converged":true,"accuracy":4.8e-10,"fermi":10.962,"total_energy":-286.908755315},{"ecutrho":100,"k_density":0.25,"ecutwfc":30,"n_iterations":33,"time":50100,"converged":true,"accuracy":5.9e-10,"fermi":10.9645,"total_energy":-286.91091556},{"ecutrho":100,"k_density":0.16666666666666666,"ecutwfc":30,"n_iterations":37,"time":164086,"converged":true,"accuracy":5.5e-10,"fermi":10.9745,"total_energy":-286.91108807},{"ecutrho":100,"k_density":0.125,"ecutwfc":30,"n_iterations":42,"time":474068,"converged":true,"accuracy":3.3e-10,"fermi":10.9813,"total_energy":-286.911048605},{"ecutrho":140,"k_density":0.1,"ecutwfc":30,"n_iterations":32,"time":696117,"converged":true,"accuracy":1.0e-9,"fermi":10.9802,"total_energy":-286.911050725},{"ecutrho":140,"k_density":0.5,"ecutwfc":30,"n_iterations":15,"time":4109,"converged":true,"accuracy":7.1e-10,"fermi":10.9621,"total_energy":-286.90874092},{"ecutrho":140,"k_density":0.25,"ecutwfc":30,"n_iterations":31,"time":42143,"converged":true,"accuracy":6.4e-10,"fermi":10.9643,"total_energy":-286.910902225},{"ecutrho":140,"k_density":0.16666666666666666,"ecutwfc":30,"n_iterations":49,"time":182160,"converged":true,"accuracy":1.8e-10,"fermi":10.9745,"total_energy":-286.91107377},{"ecutrho":140,"k_density":0.125,"ecutwfc":30,"n_iterations":36,"time":399116,"converged":true,"accuracy":5.8e-10,"fermi":10.9815,"total_energy":-286.91103429},{"ecutrho":180,"k_density":0.1,"ecutwfc":30,"n_iterations":40,"time":715108,"converged":true,"accuracy":5.1e-11,"fermi":10.9803,"total_energy":-286.9110517},{"ecutrho":180,"k_density":0.5,"ecutwfc":30,"n_iterations":15,"time":4109,"converged":true,"accuracy":8.6e-10,"fermi":10.962,"total_energy":-286.9087419},{"ecutrho":180,"k_density":0.25,"ecutwfc":30,"n_iterations":34,"time":50108,"converged":true,"accuracy":8.9e-10,"fermi":10.9647,"total_energy":-286.91090064},{"ecutrho":180,"k_density":0.16666666666666666,"ecutwfc":30,"n_iterations":34,"time":137129,"converged":true,"accuracy":3.2e-10,"fermi":10.9749,"total_energy":-286.911071395},{"ecutrho":180,"k_density":0.125,"ecutwfc":30,"n_iterations":35,"time":314150,"converged":true,"accuracy":6.4e-10,"fermi":10.9815,"total_energy":-286.91103526},{"ecutrho":220,"k_density":0.1,"ecutwfc":30,"n_iterations":33,"time":683158,"converged":true,"accuracy":3.1e-10,"fermi":10.9803,"total_energy":-286.911054195},{"ecutrho":220,"k_density":0.5,"ecutwfc":30,"n_iterations":15,"time":4125,"converged":true,"accuracy":4.5e-10,"fermi":10.9621,"total_energy":-286.90874439},{"ecutrho":220,"k_density":0.25,"ecutwfc":30,"n_iterations":67,"time":92102,"converged":true,"accuracy":6.8e-10,"fermi":10.9643,"total_energy":-286.91090624},{"ecutrho":220,"k_density":0.16666666666666666,"ecutwfc":30,"n_iterations":43,"time":190121,"converged":true,"accuracy":1.5e-10,"fermi":10.9745,"total_energy":-286.91107724},{"ecutrho":220,"k_density":0.125,"ecutwfc":30,"n_iterations":36,"time":356125,"converged":true,"accuracy":4.7e-11,"fermi":10.9814,"total_energy":-286.91103759},{"ecutrho":260,"k_density":0.1,"ecutwfc":30,"n_iterations":31,"time":674115,"converged":true,"accuracy":2.9e-11,"fermi":10.9803,"total_energy":-286.911055125},{"ecutrho":260,"k_density":0.5,"ecutwfc":30,"n_iterations":15,"time":4102,"converged":true,"accuracy":8.3e-10,"fermi":10.962,"total_energy":-286.908745405},{"ecutrho":260,"k_density":0.25,"ecutwfc":30,"n_iterations":59,"time":80126,"converged":true,"accuracy":1.8e-10,"fermi":10.9643,"total_energy":-286.910907255},{"ecutrho":260,"k_density":0.16666666666666666,"ecutwfc":30,"n_iterations":45,"time":185073,"converged":true,"accuracy":8.6e-11,"fermi":10.9745,"total_energy":-286.91107825},{"ecutrho":260,"k_density":0.125,"ecutwfc":30,"n_iterations":39,"time":382123,"converged":true,"accuracy":1.4e-10,"fermi":10.9814,"total_energy":-286.91103877},{"ecutrho":300,"k_density":0.1,"ecutwfc":30,"n_iterations":34,"time":676125,"converged":true,"accuracy":5.1e-10,"fermi":10.9803,"total_energy":-286.91105585},{"ecutrho":300,"k_density":0.5,"ecutwfc":30,"n_iterations":15,"time":4107,"converged":true,"accuracy":4.6e-10,"fermi":10.9621,"total_energy":-286.908746055},{"ecutrho":300,"k_density":0.25,"ecutwfc":30,"n_iterations":59,"time":76147,"converged":true,"accuracy":4.4e-10,"fermi":10.9642,"total_energy":-286.910907895},{"ecutrho":300,"k_density":0.16666666666666666,"ecutwfc":30,"n_iterations":55,"time":197127,"converged":true,"accuracy":8.5e-10,"fermi":10.9745,"total_energy":-286.91107889},{"ecutrho":300,"k_density":0.125,"ecutwfc":30,"n_iterations":44,"time":417123,"converged":true,"accuracy":3.4e-10,"fermi":10.9814,"total_energy":-286.91103941},{"ecutrho":340,"k_density":0.1,"ecutwfc":30,"n_iterations":30,"time":631139,"converged":true,"accuracy":3.7e-10,"fermi":10.9804,"total_energy":-286.91105612},{"ecutrho":340,"k_density":0.5,"ecutwfc":30,"n_iterations":15,"time":4120,"converged":true,"accuracy":2.8e-10,"fermi":10.9621,"total_energy":-286.908746325},{"ecutrho":340,"k_density":0.25,"ecutwfc":30,"n_iterations":32,"time":45127,"converged":true,"accuracy":7.7e-10,"fermi":10.9646,"total_energy":-286.910906095},{"ecutrho":340,"k_density":0.16666666666666666,"ecutwfc":30,"n_iterations":49,"time":182112,"converged":true,"accuracy":7.8e-10,"fermi":10.9745,"total_energy":-286.91107916},{"ecutrho":340,"k_density":0.125,"ecutwfc":30,"n_iterations":39,"time":433110,"converged":true,"accuracy":7.7e-10,"fermi":10.9813,"total_energy":-286.91103968},{"ecutrho":380,"k_density":0.1,"ecutwfc":30,"n_iterations":30,"time":665149,"converged":true,"accuracy":7.6e-11,"fermi":10.9803,"total_energy":-286.91105637},{"ecutrho":380,"k_density":0.5,"ecutwfc":30,"n_iterations":15,"time":4125,"converged":true,"accuracy":2.3e-10,"fermi":10.9621,"total_energy":-286.908746585},{"ecutrho":380,"k_density":0.25,"ecutwfc":30,"n_iterations":54,"time":82102,"converged":true,"accuracy":1.8e-10,"fermi":10.9642,"total_energy":-286.91090841},{"ecutrho":380,"k_density":0.16666666666666666,"ecutwfc":30,"n_iterations":54,"time":203092,"converged":true,"accuracy":9.0e-11,"fermi":10.9745,"total_energy":-286.911079415},{"ecutrho":380,"k_density":0.125,"ecutwfc":30,"n_iterations":36,"time":360094,"converged":true,"accuracy":1.7e-10,"fermi":10.9814,"total_energy":-286.911039935},{"ecutrho":100,"k_density":0.1,"ecutwfc":35,"n_iterations":36,"time":740158,"converged":true,"accuracy":1.5e-10,"fermi":10.9798,"total_energy":-286.911670385},{"ecutrho":100,"k_density":0.5,"ecutwfc":35,"n_iterations":16,"time":5044,"converged":true,"accuracy":1.9e-10,"fermi":10.9605,"total_energy":-286.909325215},{"ecutrho":100,"k_density":0.25,"ecutwfc":35,"n_iterations":50,"time":61088,"converged":true,"accuracy":3.2e-10,"fermi":10.9637,"total_energy":-286.91152643},{"ecutrho":100,"k_density":0.16666666666666666,"ecutwfc":35,"n_iterations":36,"time":150130,"converged":true,"accuracy":4.3e-10,"fermi":10.9739,"total_energy":-286.91169225},{"ecutrho":100,"k_density":0.125,"ecutwfc":35,"n_iterations":34,"time":345077,"converged":true,"accuracy":4.9e-10,"fermi":10.9809,"total_energy":-286.911653735},{"ecutrho":140,"k_density":0.1,"ecutwfc":35,"n_iterations":38,"time":766153,"converged":true,"accuracy":5.5e-10,"fermi":10.9798,"total_energy":-286.91165618},{"ecutrho":140,"k_density":0.5,"ecutwfc":35,"n_iterations":16,"time":5084,"converged":true,"accuracy":3.7e-10,"fermi":10.9605,"total_energy":-286.90931094},{"ecutrho":140,"k_density":0.25,"ecutwfc":35,"n_iterations":42,"time":62089,"converged":true,"accuracy":6.0e-11,"fermi":10.9638,"total_energy":-286.911511925},{"ecutrho":140,"k_density":0.16666666666666666,"ecutwfc":35,"n_iterations":34,"time":145151,"converged":true,"accuracy":8.5e-10,"fermi":10.9739,"total_energy":-286.911678175},{"ecutrho":140,"k_density":0.125,"ecutwfc":35,"n_iterations":47,"time":420132,"converged":true,"accuracy":2.1e-10,"fermi":10.9808,"total_energy":-286.91163955},{"ecutrho":180,"k_density":0.1,"ecutwfc":35,"n_iterations":36,"time":716127,"converged":true,"accuracy":7.9e-10,"fermi":10.9799,"total_energy":-286.911657145},{"ecutrho":180,"k_density":0.5,"ecutwfc":35,"n_iterations":16,"time":5055,"converged":true,"accuracy":3.7e-10,"fermi":10.9605,"total_energy":-286.90931189},{"ecutrho":180,"k_density":0.25,"ecutwfc":35,"n_iterations":34,"time":46098,"converged":true,"accuracy":4.0e-10,"fermi":10.964,"total_energy":-286.911511805},{"ecutrho":180,"k_density":0.16666666666666666,"ecutwfc":35,"n_iterations":56,"time":235156,"converged":true,"accuracy":4.3e-10,"fermi":10.974,"total_energy":-286.9116793},{"ecutrho":180,"k_density":0.125,"ecutwfc":35,"n_iterations":49,"time":443074,"converged":true,"accuracy":4.3e-10,"fermi":10.9808,"total_energy":-286.91164051},{"ecutrho":220,"k_density":0.1,"ecutwfc":35,"n_iterations":28,"time":642102,"converged":true,"accuracy":4.9e-10,"fermi":10.9798,"total_energy":-286.911659625},{"ecutrho":220,"k_density":0.5,"ecutwfc":35,"n_iterations":16,"time":5058,"converged":true,"accuracy":1.8e-10,"fermi":10.9605,"total_energy":-286.909314385},{"ecutrho":220,"k_density":0.25,"ecutwfc":35,"n_iterations":57,"time":88124,"converged":true,"accuracy":2.3e-10,"fermi":10.9636,"total_energy":-286.91151623},{"ecutrho":220,"k_density":0.16666666666666666,"ecutwfc":35,"n_iterations":58,"time":248066,"converged":true,"accuracy":2.3e-10,"fermi":10.9739,"total_energy":-286.91168179},{"ecutrho":220,"k_density":0.125,"ecutwfc":35,"n_iterations":21,"time":264114,"converged":true,"accuracy":4.6e-10,"fermi":10.9811,"total_energy":-286.911639795},{"ecutrho":260,"k_density":0.1,"ecutwfc":35,"n_iterations":37,"time":770088,"converged":true,"accuracy":8.0e-11,"fermi":10.9798,"total_energy":-286.911660645},{"ecutrho":260,"k_density":0.5,"ecutwfc":35,"n_iterations":16,"time":5059,"converged":true,"accuracy":2.5e-10,"fermi":10.9605,"total_energy":-286.9093154},{"ecutrho":260,"k_density":0.25,"ecutwfc":35,"n_iterations":64,"time":90125,"converged":true,"accuracy":7.2e-10,"fermi":10.9636,"total_energy":-286.91151727},{"ecutrho":260,"k_density":0.16666666666666666,"ecutwfc":35,"n_iterations":32,"time":130158,"converged":true,"accuracy":3.3e-10,"fermi":10.9742,"total_energy":-286.911680515},{"ecutrho":260,"k_density":0.125,"ecutwfc":35,"n_iterations":40,"time":383123,"converged":true,"accuracy":5.4e-10,"fermi":10.9808,"total_energy":-286.91164401},{"ecutrho":300,"k_density":0.1,"ecutwfc":35,"n_iterations":36,"time":773076,"converged":true,"accuracy":6.5e-10,"fermi":10.9798,"total_energy":-286.911661285},{"ecutrho":300,"k_density":0.5,"ecutwfc":35,"n_iterations":16,"time":5057,"converged":true,"accuracy":1.6e-10,"fermi":10.9605,"total_energy":-286.90931605},{"ecutrho":300,"k_density":0.25,"ecutwfc":35,"n_iterations":65,"time":81140,"converged":true,"accuracy":8.5e-10,"fermi":10.9637,"total_energy":-286.911517915},{"ecutrho":300,"k_density":0.16666666666666666,"ecutwfc":35,"n_iterations":53,"time":237124,"converged":true,"accuracy":3.7e-10,"fermi":10.974,"total_energy":-286.91168344},{"ecutrho":300,"k_density":0.125,"ecutwfc":35,"n_iterations":46,"time":469083,"converged":true,"accuracy":3.1e-10,"fermi":10.9808,"total_energy":-286.911644655},{"ecutrho":340,"k_density":0.1,"ecutwfc":35,"n_iterations":39,"time":753072,"converged":true,"accuracy":7.3e-10,"fermi":10.9798,"total_energy":-286.911661555},{"ecutrho":340,"k_density":0.5,"ecutwfc":35,"n_iterations":16,"time":5052,"converged":true,"accuracy":1.8e-10,"fermi":10.9605,"total_energy":-286.90931632},{"ecutrho":340,"k_density":0.25,"ecutwfc":35,"n_iterations":66,"time":92088,"converged":true,"accuracy":9.5e-10,"fermi":10.9636,"total_energy":-286.91151817},{"ecutrho":340,"k_density":0.16666666666666666,"ecutwfc":35,"n_iterations":48,"time":200113,"converged":true,"accuracy":9.2e-10,"fermi":10.9739,"total_energy":-286.91168371},{"ecutrho":340,"k_density":0.125,"ecutwfc":35,"n_iterations":42,"time":395103,"converged":true,"accuracy":8.7e-10,"fermi":10.9808,"total_energy":-286.91164492},{"ecutrho":380,"k_density":0.1,"ecutwfc":35,"n_iterations":38,"time":681078,"converged":true,"accuracy":7.5e-11,"fermi":10.9798,"total_energy":-286.91166181},{"ecutrho":380,"k_density":0.5,"ecutwfc":35,"n_iterations":16,"time":5074,"converged":true,"accuracy":2.6e-10,"fermi":10.9605,"total_energy":-286.90931658},{"ecutrho":380,"k_density":0.25,"ecutwfc":35,"n_iterations":62,"time":81095,"converged":true,"accuracy":1.8e-10,"fermi":10.9636,"total_energy":-286.911518435},{"ecutrho":380,"k_density":0.16666666666666666,"ecutwfc":35,"n_iterations":36,"time":169140,"converged":true,"accuracy":1.7e-10,"fermi":10.974,"total_energy":-286.91168391},{"ecutrho":380,"k_density":0.125,"ecutwfc":35,"n_iterations":40,"time":391124,"converged":true,"accuracy":2.0e-10,"fermi":10.9808,"total_energy":-286.911645175},{"ecutrho":100,"k_density":0.1,"ecutwfc":40,"n_iterations":36,"time":741131,"converged":true,"accuracy":7.5e-11,"fermi":10.9796,"total_energy":-286.91180933},{"ecutrho":100,"k_density":0.5,"ecutwfc":40,"n_iterations":14,"time":4102,"converged":true,"accuracy":2.5e-10,"fermi":10.96,"total_energy":-286.909477405},{"ecutrho":100,"k_density":0.25,"ecutwfc":40,"n_iterations":85,"time":133119,"converged":true,"accuracy":5.3e-11,"fermi":10.9634,"total_energy":-286.911663905},{"ecutrho":100,"k_density":0.16666666666666666,"ecutwfc":40,"n_iterations":36,"time":162164,"converged":true,"accuracy":1.3e-10,"fermi":10.9738,"total_energy":-286.91183325},{"ecutrho":100,"k_density":0.125,"ecutwfc":40,"n_iterations":41,"time":483166,"converged":true,"accuracy":4.6e-10,"fermi":10.9807,"total_energy":-286.91179189},{"ecutrho":140,"k_density":0.1,"ecutwfc":40,"n_iterations":28,"time":519083,"converged":true,"accuracy":8.6e-10,"fermi":10.9798,"total_energy":-286.911795},{"ecutrho":140,"k_density":0.5,"ecutwfc":40,"n_iterations":14,"time":4098,"converged":true,"accuracy":2.7e-10,"fermi":10.9601,"total_energy":-286.90946318},{"ecutrho":140,"k_density":0.25,"ecutwfc":40,"n_iterations":69,"time":99123,"converged":true,"accuracy":7.4e-10,"fermi":10.9635,"total_energy":-286.91164972},{"ecutrho":140,"k_density":0.16666666666666666,"ecutwfc":40,"n_iterations":28,"time":141090,"converged":true,"accuracy":1.9e-10,"fermi":10.9742,"total_energy":-286.911815895},{"ecutrho":140,"k_density":0.125,"ecutwfc":40,"n_iterations":42,"time":393011,"converged":true,"accuracy":2.6e-10,"fermi":10.9807,"total_energy":-286.91177774},{"ecutrho":180,"k_density":0.1,"ecutwfc":40,"n_iterations":28,"time":642096,"converged":true,"accuracy":8.2e-10,"fermi":10.9796,"total_energy":-286.91179566},{"ecutrho":180,"k_density":0.5,"ecutwfc":40,"n_iterations":14,"time":4106,"converged":true,"accuracy":1.8e-10,"fermi":10.9601,"total_energy":-286.90946413},{"ecutrho":180,"k_density":0.25,"ecutwfc":40,"n_iterations":78,"time":126089,"converged":true,"accuracy":8.3e-10,"fermi":10.9634,"total_energy":-286.91165068},{"ecutrho":180,"k_density":0.16666666666666666,"ecutwfc":40,"n_iterations":57,"time":263116,"converged":true,"accuracy":9.3e-10,"fermi":10.9738,"total_energy":-286.91182005},{"ecutrho":180,"k_density":0.125,"ecutwfc":40,"n_iterations":49,"time":491109,"converged":true,"accuracy":6.7e-10,"fermi":10.9807,"total_energy":-286.911778705},{"ecutrho":220,"k_density":0.1,"ecutwfc":40,"n_iterations":39,"time":891030,"converged":true,"accuracy":3.6e-10,"fermi":10.9797,"total_energy":-286.911798615},{"ecutrho":220,"k_density":0.5,"ecutwfc":40,"n_iterations":14,"time":4117,"converged":true,"accuracy":2.3e-10,"fermi":10.9601,"total_energy":-286.909466625},{"ecutrho":220,"k_density":0.25,"ecutwfc":40,"n_iterations":58,"time":78114,"converged":true,"accuracy":3.0e-10,"fermi":10.9634,"total_energy":-286.911653175},{"ecutrho":220,"k_density":0.16666666666666666,"ecutwfc":40,"n_iterations":42,"time":188116,"converged":true,"accuracy":3.6e-10,"fermi":10.9738,"total_energy":-286.911822535},{"ecutrho":220,"k_density":0.125,"ecutwfc":40,"n_iterations":40,"time":439091,"converged":true,"accuracy":7.5e-10,"fermi":10.9807,"total_energy":-286.911781185},{"ecutrho":260,"k_density":0.1,"ecutwfc":40,"n_iterations":31,"time":720072,"converged":true,"accuracy":3.7e-10,"fermi":10.9797,"total_energy":-286.91179963},{"ecutrho":260,"k_density":0.5,"ecutwfc":40,"n_iterations":14,"time":4124,"converged":true,"accuracy":4.6e-10,"fermi":10.96,"total_energy":-286.909467645},{"ecutrho":260,"k_density":0.25,"ecutwfc":40,"n_iterations":61,"time":84121,"converged":true,"accuracy":7.6e-10,"fermi":10.9634,"total_energy":-286.91165419},{"ecutrho":260,"k_density":0.16666666666666666,"ecutwfc":40,"n_iterations":50,"time":218162,"converged":true,"accuracy":2.9e-10,"fermi":10.9737,"total_energy":-286.91182356},{"ecutrho":260,"k_density":0.125,"ecutwfc":40,"n_iterations":42,"time":429079,"converged":true,"accuracy":5.1e-10,"fermi":10.9807,"total_energy":-286.911782215},{"ecutrho":300,"k_density":0.1,"ecutwfc":40,"n_iterations":38,"time":738044,"converged":true,"accuracy":9.0e-10,"fermi":10.9797,"total_energy":-286.911800275},{"ecutrho":300,"k_density":0.5,"ecutwfc":40,"n_iterations":14,"time":4128,"converged":true,"accuracy":5.0e-10,"fermi":10.96,"total_energy":-286.909468295},{"ecutrho":300,"k_density":0.25,"ecutwfc":40,"n_iterations":31,"time":45144,"converged":true,"accuracy":1.0e-9,"fermi":10.9642,"total_energy":-286.911650985},{"ecutrho":300,"k_density":0.16666666666666666,"ecutwfc":40,"n_iterations":52,"time":221164,"converged":true,"accuracy":2.3e-10,"fermi":10.9738,"total_energy":-286.9118242},{"ecutrho":300,"k_density":0.125,"ecutwfc":40,"n_iterations":47,"time":522081,"converged":true,"accuracy":8.4e-10,"fermi":10.9807,"total_energy":-286.911782855},{"ecutrho":340,"k_density":0.1,"ecutwfc":40,"n_iterations":36,"time":791014,"converged":true,"accuracy":4.9e-10,"fermi":10.9796,"total_energy":-286.91180055},{"ecutrho":340,"k_density":0.5,"ecutwfc":40,"n_iterations":14,"time":4125,"converged":true,"accuracy":3.6e-10,"fermi":10.96,"total_energy":-286.90946857},{"ecutrho":340,"k_density":0.25,"ecutwfc":40,"n_iterations":57,"time":79125,"converged":true,"accuracy":6.3e-10,"fermi":10.9636,"total_energy":-286.9116545},{"ecutrho":340,"k_density":0.16666666666666666,"ecutwfc":40,"n_iterations":47,"time":206091,"converged":true,"accuracy":4.8e-10,"fermi":10.9738,"total_energy":-286.911824475},{"ecutrho":340,"k_density":0.125,"ecutwfc":40,"n_iterations":30,"time":333160,"converged":true,"accuracy":5.6e-10,"fermi":10.9807,"total_energy":-286.911783105},{"ecutrho":380,"k_density":0.1,"ecutwfc":40,"n_iterations":36,"time":833063,"converged":true,"accuracy":3.7e-10,"fermi":10.9797,"total_energy":-286.9118008},{"ecutrho":380,"k_density":0.5,"ecutwfc":40,"n_iterations":14,"time":5044,"converged":true,"accuracy":6.0e-10,"fermi":10.96,"total_energy":-286.90946884},{"ecutrho":380,"k_density":0.25,"ecutwfc":40,"n_iterations":66,"time":98101,"converged":true,"accuracy":8.1e-10,"fermi":10.9634,"total_energy":-286.911655355},{"ecutrho":380,"k_density":0.16666666666666666,"ecutwfc":40,"n_iterations":47,"time":195097,"converged":true,"accuracy":7.7e-10,"fermi":10.9738,"total_energy":-286.911824725},{"ecutrho":380,"k_density":0.125,"ecutwfc":40,"n_iterations":37,"time":411173,"converged":true,"accuracy":4.8e-10,"fermi":10.9807,"total_energy":-286.911783375},{"ecutrho":100,"k_density":0.1,"ecutwfc":45,"n_iterations":41,"time":781124,"converged":true,"accuracy":7.0e-10,"fermi":10.9795,"total_energy":-286.91186459},{"ecutrho":100,"k_density":0.5,"ecutwfc":45,"n_iterations":16,"time":5061,"converged":true,"accuracy":7.8e-10,"fermi":10.9597,"total_energy":-286.909532145},{"ecutrho":100,"k_density":0.25,"ecutwfc":45,"n_iterations":70,"time":97092,"converged":true,"accuracy":5.0e-10,"fermi":10.9633,"total_energy":-286.911719935},{"ecutrho":100,"k_density":0.16666666666666666,"ecutwfc":45,"n_iterations":40,"time":191131,"converged":true,"accuracy":4.2e-10,"fermi":10.9737,"total_energy":-286.91188866},{"ecutrho":100,"k_density":0.125,"ecutwfc":45,"n_iterations":33,"time":373164,"converged":true,"accuracy":8.5e-10,"fermi":10.9806,"total_energy":-286.911847035},{"ecutrho":140,"k_density":0.1,"ecutwfc":45,"n_iterations":35,"time":745149,"converged":true,"accuracy":2.7e-10,"fermi":10.9796,"total_energy":-286.9118504},{"ecutrho":140,"k_density":0.5,"ecutwfc":45,"n_iterations":15,"time":5037,"converged":true,"accuracy":9.9e-11,"fermi":10.9598,"total_energy":-286.90951797},{"ecutrho":140,"k_density":0.25,"ecutwfc":45,"n_iterations":48,"time":72078,"converged":true,"accuracy":4.1e-10,"fermi":10.9636,"total_energy":-286.911704855},{"ecutrho":140,"k_density":0.16666666666666666,"ecutwfc":45,"n_iterations":31,"time":193148,"converged":true,"accuracy":3.7e-10,"fermi":10.9737,"total_energy":-286.91187455},{"ecutrho":140,"k_density":0.125,"ecutwfc":45,"n_iterations":43,"time":487045,"converged":true,"accuracy":9.1e-10,"fermi":10.9807,"total_energy":-286.91183295},{"ecutrho":180,"k_density":0.1,"ecutwfc":45,"n_iterations":34,"time":761178,"converged":true,"accuracy":2.0e-10,"fermi":10.9795,"total_energy":-286.91185136},{"ecutrho":180,"k_density":0.5,"ecutwfc":45,"n_iterations":15,"time":5046,"converged":true,"accuracy":5.6e-10,"fermi":10.9598,"total_energy":-286.90951891},{"ecutrho":180,"k_density":0.25,"ecutwfc":45,"n_iterations":59,"time":77143,"converged":true,"accuracy":4.5e-10,"fermi":10.9634,"total_energy":-286.91170677},{"ecutrho":180,"k_density":0.16666666666666666,"ecutwfc":45,"n_iterations":32,"time":227147,"converged":true,"accuracy":1.8e-10,"fermi":10.9737,"total_energy":-286.91187551},{"ecutrho":180,"k_density":0.125,"ecutwfc":45,"n_iterations":37,"time":413089,"converged":true,"accuracy":7.9e-10,"fermi":10.9806,"total_energy":-286.911833915},{"ecutrho":220,"k_density":0.1,"ecutwfc":45,"n_iterations":33,"time":748148,"converged":true,"accuracy":7.6e-10,"fermi":10.9795,"total_energy":-286.911853935},{"ecutrho":220,"k_density":0.5,"ecutwfc":45,"n_iterations":15,"time":5057,"converged":true,"accuracy":5.5e-10,"fermi":10.9597,"total_energy":-286.909521425},{"ecutrho":220,"k_density":0.25,"ecutwfc":45,"n_iterations":63,"time":82089,"converged":true,"accuracy":1.9e-11,"fermi":10.9633,"total_energy":-286.911709265},{"ecutrho":220,"k_density":0.16666666666666666,"ecutwfc":45,"n_iterations":43,"time":236165,"converged":true,"accuracy":9.3e-10,"fermi":10.9736,"total_energy":-286.911878005},{"ecutrho":220,"k_density":0.125,"ecutwfc":45,"n_iterations":52,"time":547108,"converged":true,"accuracy":3.8e-10,"fermi":10.9807,"total_energy":-286.911836415},{"ecutrho":260,"k_density":0.1,"ecutwfc":45,"n_iterations":33,"time":869092,"converged":true,"accuracy":6.2e-10,"fermi":10.9796,"total_energy":-286.91185496},{"ecutrho":260,"k_density":0.5,"ecutwfc":45,"n_iterations":15,"time":5062,"converged":true,"accuracy":5.5e-10,"fermi":10.9598,"total_energy":-286.90952244},{"ecutrho":260,"k_density":0.25,"ecutwfc":45,"n_iterations":39,"time":60168,"converged":true,"accuracy":1.5e-10,"fermi":10.9636,"total_energy":-286.91170915},{"ecutrho":260,"k_density":0.16666666666666666,"ecutwfc":45,"n_iterations":41,"time":277146,"converged":true,"accuracy":7.0e-11,"fermi":10.9737,"total_energy":-286.91187903},{"ecutrho":260,"k_density":0.125,"ecutwfc":45,"n_iterations":39,"time":453055,"converged":true,"accuracy":5.7e-10,"fermi":10.9806,"total_energy":-286.911837345},{"ecutrho":300,"k_density":0.1,"ecutwfc":45,"n_iterations":33,"time":801086,"converged":true,"accuracy":1.3e-10,"fermi":10.9795,"total_energy":-286.9118556},{"ecutrho":300,"k_density":0.5,"ecutwfc":45,"n_iterations":15,"time":5059,"converged":true,"accuracy":5.5e-10,"fermi":10.9598,"total_energy":-286.90952309},{"ecutrho":300,"k_density":0.25,"ecutwfc":45,"n_iterations":58,"time":74089,"converged":true,"accuracy":8.8e-10,"fermi":10.9633,"total_energy":-286.91171093},{"ecutrho":300,"k_density":0.16666666666666666,"ecutwfc":45,"n_iterations":31,"time":195137,"converged":true,"accuracy":8.1e-10,"fermi":10.9736,"total_energy":-286.911879655},{"ecutrho":300,"k_density":0.125,"ecutwfc":45,"n_iterations":28,"time":368085,"converged":true,"accuracy":9.4e-10,"fermi":10.9807,"total_energy":-286.911837755},{"ecutrho":340,"k_density":0.1,"ecutwfc":45,"n_iterations":31,"time":722130,"converged":true,"accuracy":4.0e-10,"fermi":10.9796,"total_energy":-286.911855875},{"ecutrho":340,"k_density":0.5,"ecutwfc":45,"n_iterations":15,"time":5058,"converged":true,"accuracy":6.1e-10,"fermi":10.9598,"total_energy":-286.909523365},{"ecutrho":340,"k_density":0.25,"ecutwfc":45,"n_iterations":61,"time":94117,"converged":true,"accuracy":3.9e-10,"fermi":10.9634,"total_energy":-286.911711205},{"ecutrho":340,"k_density":0.16666666666666666,"ecutwfc":45,"n_iterations":33,"time":198153,"converged":true,"accuracy":5.1e-11,"fermi":10.9737,"total_energy":-286.911879945},{"ecutrho":340,"k_density":0.125,"ecutwfc":45,"n_iterations":48,"time":483056,"converged":true,"accuracy":2.2e-10,"fermi":10.9806,"total_energy":-286.911838355},{"ecutrho":380,"k_density":0.1,"ecutwfc":45,"n_iterations":29,"time":698179,"converged":true,"accuracy":3.7e-10,"fermi":10.9796,"total_energy":-286.911856125},{"ecutrho":380,"k_density":0.5,"ecutwfc":45,"n_iterations":15,"time":5069,"converged":true,"accuracy":5.8e-10,"fermi":10.9598,"total_energy":-286.909523625},{"ecutrho":380,"k_density":0.25,"ecutwfc":45,"n_iterations":55,"time":81129,"converged":true,"accuracy":3.0e-10,"fermi":10.9633,"total_energy":-286.911711455},{"ecutrho":380,"k_density":0.16666666666666666,"ecutwfc":45,"n_iterations":36,"time":216143,"converged":true,"accuracy":3.5e-10,"fermi":10.9737,"total_energy":-286.911880195},{"ecutrho":380,"k_density":0.125,"ecutwfc":45,"n_iterations":42,"time":466080,"converged":true,"accuracy":1.4e-10,"fermi":10.9806,"total_energy":-286.911838605},{"ecutrho":100,"k_density":0.1,"ecutwfc":50,"n_iterations":36,"time":898066,"converged":true,"accuracy":8.8e-10,"fermi":10.9794,"total_energy":-286.91193146},{"ecutrho":100,"k_density":0.5,"ecutwfc":50,"n_iterations":16,"time":5053,"converged":true,"accuracy":7.9e-10,"fermi":10.9593,"total_energy":-286.909601145},{"ecutrho":100,"k_density":0.25,"ecutwfc":50,"n_iterations":59,"time":86164,"converged":true,"accuracy":7.3e-10,"fermi":10.9633,"total_energy":-286.911785935},{"ecutrho":100,"k_density":0.16666666666666666,"ecutwfc":50,"n_iterations":37,"time":185160,"converged":true,"accuracy":4.6e-11,"fermi":10.9737,"total_energy":-286.911954835},{"ecutrho":100,"k_density":0.125,"ecutwfc":50,"n_iterations":45,"time":418172,"converged":true,"accuracy":9.7e-11,"fermi":10.9805,"total_energy":-286.91191369},{"ecutrho":140,"k_density":0.1,"ecutwfc":50,"n_iterations":43,"time":1033131,"converged":true,"accuracy":1.4e-10,"fermi":10.9795,"total_energy":-286.91191759},{"ecutrho":140,"k_density":0.5,"ecutwfc":50,"n_iterations":15,"time":4122,"converged":true,"accuracy":8.9e-10,"fermi":10.9594,"total_energy":-286.909587225},{"ecutrho":140,"k_density":0.25,"ecutwfc":50,"n_iterations":58,"time":87090,"converged":true,"accuracy":4.8e-10,"fermi":10.9633,"total_energy":-286.91177205},{"ecutrho":140,"k_density":0.16666666666666666,"ecutwfc":50,"n_iterations":47,"time":234177,"converged":true,"accuracy":3.5e-11,"fermi":10.9736,"total_energy":-286.911941195},{"ecutrho":140,"k_density":0.125,"ecutwfc":50,"n_iterations":45,"time":460026,"converged":true,"accuracy":9.3e-11,"fermi":10.9806,"total_energy":-286.911899815},{"ecutrho":180,"k_density":0.1,"ecutwfc":50,"n_iterations":35,"time":845085,"converged":true,"accuracy":8.0e-10,"fermi":10.9795,"total_energy":-286.91191854},{"ecutrho":180,"k_density":0.5,"ecutwfc":50,"n_iterations":15,"time":5036,"converged":true,"accuracy":5.8e-10,"fermi":10.9594,"total_energy":-286.90958816},{"ecutrho":180,"k_density":0.25,"ecutwfc":50,"n_iterations":66,"time":107090,"converged":true,"accuracy":5.8e-11,"fermi":10.9633,"total_energy":-286.911773},{"ecutrho":180,"k_density":0.16666666666666666,"ecutwfc":50,"n_iterations":50,"time":215162,"converged":true,"accuracy":3.4e-10,"fermi":10.9737,"total_energy":-286.91194215},{"ecutrho":180,"k_density":0.125,"ecutwfc":50,"n_iterations":29,"time":356074,"converged":true,"accuracy":2.6e-10,"fermi":10.9806,"total_energy":-286.91190046},{"ecutrho":220,"k_density":0.1,"ecutwfc":50,"n_iterations":37,"time":773036,"converged":true,"accuracy":8.8e-10,"fermi":10.9793,"total_energy":-286.91192103},{"ecutrho":220,"k_density":0.5,"ecutwfc":50,"n_iterations":14,"time":4111,"converged":true,"accuracy":9.1e-10,"fermi":10.9595,"total_energy":-286.90959065},{"ecutrho":220,"k_density":0.25,"ecutwfc":50,"n_iterations":57,"time":88102,"converged":true,"accuracy":4.0e-10,"fermi":10.9633,"total_energy":-286.911775385},{"ecutrho":220,"k_density":0.16666666666666666,"ecutwfc":50,"n_iterations":35,"time":179119,"converged":true,"accuracy":2.0e-10,"fermi":10.9737,"total_energy":-286.91194372},{"ecutrho":220,"k_density":0.125,"ecutwfc":50,"n_iterations":36,"time":418108,"converged":true,"accuracy":9.4e-11,"fermi":10.9805,"total_energy":-286.911903255},{"ecutrho":260,"k_density":0.1,"ecutwfc":50,"n_iterations":30,"time":676091,"converged":true,"accuracy":5.0e-10,"fermi":10.9795,"total_energy":-286.911922045},{"ecutrho":260,"k_density":0.5,"ecutwfc":50,"n_iterations":15,"time":5046,"converged":true,"accuracy":6.1e-10,"fermi":10.9593,"total_energy":-286.90959168},{"ecutrho":260,"k_density":0.25,"ecutwfc":50,"n_iterations":60,"time":96167,"converged":true,"accuracy":2.5e-10,"fermi":10.9633,"total_energy":-286.91177651},{"ecutrho":260,"k_density":0.16666666666666666,"ecutwfc":50,"n_iterations":33,"time":187181,"converged":true,"accuracy":5.1e-10,"fermi":10.9737,"total_energy":-286.91194508},{"ecutrho":260,"k_density":0.125,"ecutwfc":50,"n_iterations":30,"time":325123,"converged":true,"accuracy":2.7e-10,"fermi":10.9806,"total_energy":-286.911904015},{"ecutrho":300,"k_density":0.1,"ecutwfc":50,"n_iterations":35,"time":852094,"converged":true,"accuracy":2.6e-10,"fermi":10.9795,"total_energy":-286.911922695},{"ecutrho":300,"k_density":0.5,"ecutwfc":50,"n_iterations":15,"time":5043,"converged":true,"accuracy":4.7e-10,"fermi":10.9594,"total_energy":-286.90959233},{"ecutrho":300,"k_density":0.25,"ecutwfc":50,"n_iterations":67,"time":94169,"converged":true,"accuracy":7.9e-10,"fermi":10.9633,"total_energy":-286.911777155},{"ecutrho":300,"k_density":0.16666666666666666,"ecutwfc":50,"n_iterations":34,"time":168081,"converged":true,"accuracy":9.9e-10,"fermi":10.9737,"total_energy":-286.911945685},{"ecutrho":300,"k_density":0.125,"ecutwfc":50,"n_iterations":37,"time":446038,"converged":true,"accuracy":4.5e-10,"fermi":10.9805,"total_energy":-286.911904905},{"ecutrho":340,"k_density":0.1,"ecutwfc":50,"n_iterations":44,"time":915047,"converged":true,"accuracy":6.9e-10,"fermi":10.9794,"total_energy":-286.911922975},{"ecutrho":340,"k_density":0.5,"ecutwfc":50,"n_iterations":15,"time":5051,"converged":true,"accuracy":6.4e-10,"fermi":10.9593,"total_energy":-286.909592605},{"ecutrho":340,"k_density":0.25,"ecutwfc":50,"n_iterations":57,"time":77094,"converged":true,"accuracy":9.9e-10,"fermi":10.9633,"total_energy":-286.91177743},{"ecutrho":340,"k_density":0.16666666666666666,"ecutwfc":50,"n_iterations":30,"time":153176,"converged":true,"accuracy":7.2e-10,"fermi":10.9738,"total_energy":-286.91194551},{"ecutrho":340,"k_density":0.125,"ecutwfc":50,"n_iterations":39,"time":464121,"converged":true,"accuracy":5.2e-10,"fermi":10.9806,"total_energy":-286.91190508},{"ecutrho":380,"k_density":0.1,"ecutwfc":50,"n_iterations":39,"time":818039,"converged":true,"accuracy":2.4e-11,"fermi":10.9794,"total_energy":-286.91192322},{"ecutrho":380,"k_density":0.5,"ecutwfc":50,"n_iterations":15,"time":5071,"converged":true,"accuracy":5.0e-10,"fermi":10.9594,"total_energy":-286.909592865},{"ecutrho":380,"k_density":0.25,"ecutwfc":50,"n_iterations":58,"time":98106,"converged":true,"accuracy":4.4e-10,"fermi":10.9632,"total_energy":-286.91177766},{"ecutrho":380,"k_density":0.16666666666666666,"ecutwfc":50,"n_iterations":52,"time":250128,"converged":true,"accuracy":7.8e-10,"fermi":10.9736,"total_energy":-286.91194683},{"ecutrho":380,"k_density":0.125,"ecutwfc":50,"n_iterations":31,"time":411059,"converged":true,"accuracy":4.5e-10,"fermi":10.9806,"total_energy":-286.911905225},{"ecutrho":100,"k_density":0.1,"ecutwfc":55,"n_iterations":35,"time":679093,"converged":true,"accuracy":4.7e-10,"fermi":10.9795,"total_energy":-286.91196889},{"ecutrho":100,"k_density":0.5,"ecutwfc":55,"n_iterations":14,"time":4088,"converged":true,"accuracy":6.1e-10,"fermi":10.9592,"total_energy":-286.909639395},{"ecutrho":100,"k_density":0.25,"ecutwfc":55,"n_iterations":79,"time":124103,"converged":true,"accuracy":7.8e-10,"fermi":10.9633,"total_energy":-286.911823525},{"ecutrho":100,"k_density":0.16666666666666666,"ecutwfc":55,"n_iterations":42,"time":197088,"converged":true,"accuracy":5.7e-10,"fermi":10.9736,"total_energy":-286.91199265},{"ecutrho":100,"k_density":0.125,"ecutwfc":55,"n_iterations":38,"time":458106,"converged":true,"accuracy":5.7e-10,"fermi":10.9805,"total_energy":-286.911951305},{"ecutrho":140,"k_density":0.1,"ecutwfc":55,"n_iterations":34,"time":883155,"converged":true,"accuracy":3.0e-10,"fermi":10.9795,"total_energy":-286.911955235},{"ecutrho":140,"k_density":0.5,"ecutwfc":55,"n_iterations":15,"time":5047,"converged":true,"accuracy":1.2e-11,"fermi":10.9594,"total_energy":-286.909625635},{"ecutrho":140,"k_density":0.25,"ecutwfc":55,"n_iterations":68,"time":114168,"converged":true,"accuracy":5.9e-10,"fermi":10.9633,"total_energy":-286.911809745},{"ecutrho":140,"k_density":0.16666666666666666,"ecutwfc":55,"n_iterations":50,"time":220169,"converged":true,"accuracy":5.1e-10,"fermi":10.9736,"total_energy":-286.911978915},{"ecutrho":140,"k_density":0.125,"ecutwfc":55,"n_iterations":38,"time":408118,"converged":true,"accuracy":3.0e-10,"fermi":10.9805,"total_energy":-286.911937575},{"ecutrho":180,"k_density":0.1,"ecutwfc":55,"n_iterations":38,"time":820081,"converged":true,"accuracy":7.8e-11,"fermi":10.9794,"total_energy":-286.91195619},{"ecutrho":180,"k_density":0.5,"ecutwfc":55,"n_iterations":15,"time":5062,"converged":true,"accuracy":1.3e-11,"fermi":10.9594,"total_energy":-286.90962657},{"ecutrho":180,"k_density":0.25,"ecutwfc":55,"n_iterations":27,"time":48167,"converged":true,"accuracy":8.7e-10,"fermi":10.9641,"total_energy":-286.911805475},{"ecutrho":180,"k_density":0.16666666666666666,"ecutwfc":55,"n_iterations":28,"time":163153,"converged":true,"accuracy":9.9e-10,"fermi":10.9738,"total_energy":-286.91197853},{"ecutrho":180,"k_density":0.125,"ecutwfc":55,"n_iterations":44,"time":510056,"converged":true,"accuracy":6.2e-10,"fermi":10.9805,"total_energy":-286.91193854},{"ecutrho":220,"k_density":0.1,"ecutwfc":55,"n_iterations":37,"time":895062,"converged":true,"accuracy":7.1e-11,"fermi":10.9795,"total_energy":-286.911958655},{"ecutrho":220,"k_density":0.5,"ecutwfc":55,"n_iterations":15,"time":5087,"converged":true,"accuracy":1.3e-11,"fermi":10.9594,"total_energy":-286.90962905},{"ecutrho":220,"k_density":0.25,"ecutwfc":55,"n_iterations":32,"time":56160,"converged":true,"accuracy":4.2e-10,"fermi":10.964,"total_energy":-286.9118095},{"ecutrho":220,"k_density":0.16666666666666666,"ecutwfc":55,"n_iterations":27,"time":154040,"converged":true,"accuracy":4.1e-10,"fermi":10.9737,"total_energy":-286.911981805},{"ecutrho":220,"k_density":0.125,"ecutwfc":55,"n_iterations":38,"time":444103,"converged":true,"accuracy":3.2e-10,"fermi":10.9805,"total_energy":-286.911941015},{"ecutrho":260,"k_density":0.1,"ecutwfc":55,"n_iterations":33,"time":843057,"converged":true,"accuracy":7.0e-11,"fermi":10.9795,"total_energy":-286.91195969},{"ecutrho":260,"k_density":0.5,"ecutwfc":55,"n_iterations":15,"time":5085,"converged":true,"accuracy":1.4e-11,"fermi":10.9594,"total_energy":-286.909630075},{"ecutrho":260,"k_density":0.25,"ecutwfc":55,"n_iterations":33,"time":56120,"converged":true,"accuracy":2.9e-10,"fermi":10.964,"total_energy":-286.911810555},{"ecutrho":260,"k_density":0.16666666666666666,"ecutwfc":55,"n_iterations":38,"time":197056,"converged":true,"accuracy":9.1e-10,"fermi":10.9736,"total_energy":-286.911983375},{"ecutrho":260,"k_density":0.125,"ecutwfc":55,"n_iterations":45,"time":476084,"converged":true,"accuracy":3.3e-10,"fermi":10.9806,"total_energy":-286.911942035},{"ecutrho":300,"k_density":0.5,"ecutwfc":55,"n_iterations":15,"time":5087,"converged":true,"accuracy":1.6e-10,"fermi":10.9594,"total_energy":-286.909630725}]