[{"ecutrho":140,"k_density":0.1,"ecutwfc":100,"n_iterations":11,"time":143144,"converged":true,"accuracy":5.1e-10,"fermi":12.7113,"total_energy":-55.3511021},{"ecutrho":140,"k_density":0.5,"ecutwfc":100,"n_iterations":21,"time":1100,"converged":true,"accuracy":1.9e-11,"fermi":12.4808,"total_energy":-55.34480449},{"ecutrho":140,"k_density":0.25,"ecutwfc":100,"n_iterations":14,"time":9112,"converged":true,"accuracy":2.8e-11,"fermi":12.781,"total_energy":-55.351574185},{"ecutrho":140,"k_density":0.16666666666666666,"ecutwfc":100,"n_iterations":13,"time":33189,"converged":true,"accuracy":8.4e-10,"fermi":12.6915,"total_energy":-55.350597785},{"ecutrho":140,"k_density":0.125,"ecutwfc":100,"n_iterations":12,"time":78100,"converged":true,"accuracy":6.3e-11,"fermi":12.7348,"total_energy":-55.35117625},{"ecutrho":180,"k_density":0.5,"ecutwfc":100,"n_iterations":22,"time":1117,"converged":true,"accuracy":3.0e-10,"fermi":12.48,"total_energy":-55.34454351},{"ecutrho":180,"k_density":0.25,"ecutwfc":100,"n_iterations":15,"time":11067,"converged":true,"accuracy":1.8e-10,"fermi":12.7801,"total_energy":-55.351314025},{"ecutrho":180,"k_density":0.16666666666666666,"ecutwfc":100,"n_iterations":14,"time":36147,"converged":true,"accuracy":2.6e-10,"fermi":12.6906,"total_energy":-55.35033738},{"ecutrho":220,"k_density":0.1,"ecutwfc":100,"n_iterations":12,"time":163032,"converged":true,"accuracy":6.2e-11,"fermi":12.7105,"total_energy":-55.35089558},{"ecutrho":220,"k_density":0.5,"ecutwfc":100,"n_iterations":22,"time":2025,"converged":true,"accuracy":5.1e-12,"fermi":12.4801,"total_energy":-55.344596335},{"ecutrho":220,"k_density":0.25,"ecutwfc":100,"n_iterations":15,"time":10106,"converged":true,"accuracy":3.5e-10,"fermi":12.7802,"total_energy":-55.35136819},{"ecutrho":220,"k_density":0.16666666666666666,"ecutwfc":100,"n_iterations":13,"time":35156,"converged":true,"accuracy":8.2e-10,"fermi":12.6908,"total_energy":-55.35039125},{"ecutrho":220,"k_density":0.125,"ecutwfc":100,"n_iterations":12,"time":81018,"converged":true,"accuracy":6.6e-11,"fermi":12.734,"total_energy":-55.350969745},{"ecutrho":260,"k_density":0.1,"ecutwfc":100,"n_iterations":12,"time":175133,"converged":true,"accuracy":8.9e-11,"fermi":12.7104,"total_energy":-55.35089423},{"ecutrho":260,"k_density":0.5,"ecutwfc":100,"n_iterations":21,"time":2041,"converged":true,"accuracy":7.8e-10,"fermi":12.48,"total_energy":-55.34459373},{"ecutrho":260,"k_density":0.25,"ecutwfc":100,"n_iterations":15,"time":11110,"converged":true,"accuracy":6.0e-11,"fermi":12.7801,"total_energy":-55.351367215},{"ecutrho":260,"k_density":0.16666666666666666,"ecutwfc":100,"n_iterations":14,"time":41014,"converged":true,"accuracy":2.0e-10,"fermi":12.6906,"total_energy":-55.350389905},{"ecutrho":260,"k_density":0.125,"ecutwfc":100,"n_iterations":12,"time":87128,"converged":true,"accuracy":8.3e-11,"fermi":12.7339,"total_energy":-55.35096829},{"ecutrho":300,"k_density":0.1,"ecutwfc":100,"n_iterations":12,"time":189185,"converged":true,"accuracy":8.3e-11,"fermi":12.7103,"total_energy":-55.3508921},{"ecutrho":300,"k_density":0.5,"ecutwfc":100,"n_iterations":22,"time":2080,"converged":true,"accuracy":8.8e-11,"fermi":12.4799,"total_energy":-55.344591285},{"ecutrho":300,"k_density":0.25,"ecutwfc":100,"n_iterations":15,"time":12132,"converged":true,"accuracy":6.9e-11,"fermi":12.7801,"total_energy":-55.351365175},{"ecutrho":300,"k_density":0.16666666666666666,"ecutwfc":100,"n_iterations":14,"time":44072,"converged":true,"accuracy":1.2e-10,"fermi":12.6906,"total_energy":-55.35038778},{"ecutrho":300,"k_density":0.125,"ecutwfc":100,"n_iterations":12,"time":94136,"converged":true,"accuracy":7.9e-11,"fermi":12.7339,"total_energy":-55.350966125},{"ecutrho":340,"k_density":0.1,"ecutwfc":100,"n_iterations":12,"time":189159,"converged":true,"accuracy":8.4e-11,"fermi":12.7103,"total_energy":-55.350897915},{"ecutrho":340,"k_density":0.5,"ecutwfc":100,"n_iterations":20,"time":2054,"converged":true,"accuracy":1.1e-10,"fermi":12.4799,"total_energy":-55.344597035},{"ecutrho":340,"k_density":0.25,"ecutwfc":100,"n_iterations":15,"time":12139,"converged":true,"accuracy":3.7e-11,"fermi":12.7801,"total_energy":-55.351371025},{"ecutrho":340,"k_density":0.16666666666666666,"ecutwfc":100,"n_iterations":14,"time":45042,"converged":true,"accuracy":1.2e-10,"fermi":12.6906,"total_energy":-55.35039359},{"ecutrho":380,"k_density":0.1,"ecutwfc":100,"n_iterations":12,"time":194010,"converged":true,"accuracy":8.6e-11,"fermi":12.7103,"total_energy":-55.35089617},{"ecutrho":380,"k_density":0.5,"ecutwfc":100,"n_iterations":21,"time":2072,"converged":true,"accuracy":5.8e-10,"fermi":12.48,"total_energy":-55.344595425},{"ecutrho":380,"k_density":0.25,"ecutwfc":100,"n_iterations":15,"time":13050,"converged":true,"accuracy":5.3e-11,"fermi":12.7801,"total_energy":-55.351369225},{"ecutrho":380,"k_density":0.125,"ecutwfc":100,"n_iterations":12,"time":95128,"converged":true,"accuracy":8.0e-11,"fermi":12.7339,"total_energy":-55.350970205},{"ecutrho":100,"k_density":0.1,"ecutwfc":20,"n_iterations":10,"time":98101,"converged":true,"accuracy":5.8e-11,"fermi":12.8385,"total_energy":-55.32027146},{"ecutrho":100,"k_density":0.5,"ecutwfc":20,"n_iterations":21,"time":1068,"converged":true,"accuracy":4.8e-10,"fermi":12.5909,"total_energy":-55.31584045},{"ecutrho":100,"k_density":0.25,"ecutwfc":20,"n_iterations":12,"time":6110,"converged":true,"accuracy":3.6e-10,"fermi":12.9126,"total_energy":-55.32098348},{"ecutrho":100,"k_density":0.16666666666666666,"ecutwfc":20,"n_iterations":11,"time":21142,"converged":true,"accuracy":3.3e-10,"fermi":12.8126,"total_energy":-55.31991165},{"ecutrho":100,"k_density":0.125,"ecutwfc":20,"n_iterations":10,"time":49073,"converged":true,"accuracy":2.7e-10,"fermi":12.8592,"total_energy":-55.319945415},{"ecutrho":140,"k_density":0.1,"ecutwfc":20,"n_iterations":10,"time":96163,"converged":true,"accuracy":2.5e-10,"fermi":12.8192,"total_energy":-55.31736598},{"ecutrho":140,"k_density":0.5,"ecutwfc":20,"n_iterations":17,"time":1037,"converged":true,"accuracy":1.6e-10,"fermi":12.5708,"total_energy":-55.312846305},{"ecutrho":140,"k_density":0.25,"ecutwfc":20,"n_iterations":11,"time":6073,"converged":true,"accuracy":1.1e-10,"fermi":12.8936,"total_energy":-55.318094535},{"ecutrho":140,"k_density":0.16666666666666666,"ecutwfc":20,"n_iterations":13,"time":25091,"converged":true,"accuracy":1.7e-10,"fermi":12.7932,"total_energy":-55.31700745},{"ecutrho":140,"k_density":0.125,"ecutwfc":20,"n_iterations":9,"time":45070,"converged":true,"accuracy":9.8e-10,"fermi":12.8399,"total_energy":-55.317039435},{"ecutrho":180,"k_density":0.1,"ecutwfc":20,"n_iterations":10,"time":98009,"converged":true,"accuracy":2.5e-10,"fermi":12.8184,"total_energy":-55.31705275},{"ecutrho":180,"k_density":0.5,"ecutwfc":20,"n_iterations":18,"time":1063,"converged":true,"accuracy":7.6e-10,"fermi":12.5701,"total_energy":-55.312533575},{"ecutrho":180,"k_density":0.25,"ecutwfc":20,"n_iterations":11,"time":6079,"converged":true,"accuracy":9.7e-11,"fermi":12.8929,"total_energy":-55.31778247},{"ecutrho":180,"k_density":0.16666666666666666,"ecutwfc":20,"n_iterations":13,"time":25129,"converged":true,"accuracy":1.7e-10,"fermi":12.7924,"total_energy":-55.31669433},{"ecutrho":180,"k_density":0.125,"ecutwfc":20,"n_iterations":10,"time":49061,"converged":true,"accuracy":2.3e-10,"fermi":12.8391,"total_energy":-55.316725925},{"ecutrho":220,"k_density":0.1,"ecutwfc":20,"n_iterations":10,"time":96083,"converged":true,"accuracy":2.4e-10,"fermi":12.8185,"total_energy":-55.317130025},{"ecutrho":220,"k_density":0.5,"ecutwfc":20,"n_iterations":26,"time":1110,"converged":true,"accuracy":7.6e-10,"fermi":12.5701,"total_energy":-55.312609085},{"ecutrho":220,"k_density":0.25,"ecutwfc":20,"n_iterations":11,"time":6070,"converged":true,"accuracy":1.1e-10,"fermi":12.893,"total_energy":-55.31785967},{"ecutrho":220,"k_density":0.16666666666666666,"ecutwfc":20,"n_iterations":13,"time":25104,"converged":true,"accuracy":1.4e-10,"fermi":12.7926,"total_energy":-55.31677155},{"ecutrho":220,"k_density":0.125,"ecutwfc":20,"n_iterations":10,"time":49102,"converged":true,"accuracy":2.2e-10,"fermi":12.8392,"total_energy":-55.31680334},{"ecutrho":260,"k_density":0.1,"ecutwfc":20,"n_iterations":10,"time":98069,"converged":true,"accuracy":2.4e-10,"fermi":12.8184,"total_energy":-55.31712889},{"ecutrho":260,"k_density":0.5,"ecutwfc":20,"n_iterations":20,"time":1080,"converged":true,"accuracy":5.2e-10,"fermi":12.57,"total_energy":-55.31260631},{"ecutrho":260,"k_density":0.25,"ecutwfc":20,"n_iterations":11,"time":6074,"converged":true,"accuracy":8.2e-11,"fermi":12.8928,"total_energy":-55.31785905},{"ecutrho":260,"k_density":0.16666666666666666,"ecutwfc":20,"n_iterations":13,"time":25107,"converged":true,"accuracy":1.5e-10,"fermi":12.7924,"total_energy":-55.316770465},{"ecutrho":260,"k_density":0.125,"ecutwfc":20,"n_iterations":10,"time":48108,"converged":true,"accuracy":2.2e-10,"fermi":12.839,"total_energy":-55.31680205},{"ecutrho":300,"k_density":0.1,"ecutwfc":20,"n_iterations":10,"time":98041,"converged":true,"accuracy":2.3e-10,"fermi":12.8183,"total_energy":-55.317123545},{"ecutrho":300,"k_density":0.5,"ecutwfc":20,"n_iterations":17,"time":1056,"converged":true,"accuracy":2.7e-10,"fermi":12.57,"total_energy":-55.31260072},{"ecutrho":300,"k_density":0.25,"ecutwfc":20,"n_iterations":11,"time":6073,"converged":true,"accuracy":8.4e-11,"fermi":12.8928,"total_energy":-55.31785383},{"ecutrho":300,"k_density":0.16666666666666666,"ecutwfc":20,"n_iterations":13,"time":25123,"converged":true,"accuracy":1.6e-10,"fermi":12.7923,"total_energy":-55.316765165},{"ecutrho":300,"k_density":0.125,"ecutwfc":20,"n_iterations":10,"time":49069,"converged":true,"accuracy":2.3e-10,"fermi":12.839,"total_energy":-55.31679662},{"ecutrho":340,"k_density":0.1,"ecutwfc":20,"n_iterations":10,"time":98053,"converged":true,"accuracy":2.3e-10,"fermi":12.8183,"total_energy":-55.317130305},{"ecutrho":340,"k_density":0.5,"ecutwfc":20,"n_iterations":18,"time":1065,"converged":true,"accuracy":1.3e-10,"fermi":12.57,"total_energy":-55.312607375},{"ecutrho":340,"k_density":0.25,"ecutwfc":20,"n_iterations":11,"time":6074,"converged":true,"accuracy":8.4e-11,"fermi":12.8928,"total_energy":-55.31786062},{"ecutrho":340,"k_density":0.16666666666666666,"ecutwfc":20,"n_iterations":13,"time":25084,"converged":true,"accuracy":1.6e-10,"fermi":12.7923,"total_energy":-55.316771925},{"ecutrho":340,"k_density":0.125,"ecutwfc":20,"n_iterations":10,"time":49093,"converged":true,"accuracy":2.3e-10,"fermi":12.839,"total_energy":-55.31680338},{"ecutrho":380,"k_density":0.1,"ecutwfc":20,"n_iterations":10,"time":97025,"converged":true,"accuracy":2.4e-10,"fermi":12.8183,"total_energy":-55.31712944},{"ecutrho":380,"k_density":0.5,"ecutwfc":20,"n_iterations":17,"time":1065,"converged":true,"accuracy":3.1e-10,"fermi":12.57,"total_energy":-55.312606665},{"ecutrho":380,"k_density":0.25,"ecutwfc":20,"n_iterations":11,"time":6071,"converged":true,"accuracy":8.5e-11,"fermi":12.8928,"total_energy":-55.317859685},{"ecutrho":380,"k_density":0.16666666666666666,"ecutwfc":20,"n_iterations":13,"time":25112,"converged":true,"accuracy":1.6e-10,"fermi":12.7924,"total_energy":-55.31677104},{"ecutrho":380,"k_density":0.125,"ecutwfc":20,"n_iterations":10,"time":48122,"converged":true,"accuracy":2.3e-10,"fermi":12.839,"total_energy":-55.316802555},{"ecutrho":100,"k_density":0.1,"ecutwfc":25,"n_iterations":9,"time":86066,"converged":true,"accuracy":2.7e-10,"fermi":12.7674,"total_energy":-55.341876995},{"ecutrho":100,"k_density":0.5,"ecutwfc":25,"n_iterations":19,"time":1050,"converged":true,"accuracy":5.4e-11,"fermi":12.5319,"total_energy":-55.33540449},{"ecutrho":100,"k_density":0.25,"ecutwfc":25,"n_iterations":11,"time":6087,"converged":true,"accuracy":6.5e-10,"fermi":12.8313,"total_energy":-55.342699055},{"ecutrho":100,"k_density":0.16666666666666666,"ecutwfc":25,"n_iterations":11,"time":23109,"converged":true,"accuracy":6.5e-12,"fermi":12.7468,"total_energy":-55.341268485},{"ecutrho":100,"k_density":0.125,"ecutwfc":25,"n_iterations":9,"time":44085,"converged":true,"accuracy":3.0e-10,"fermi":12.7924,"total_energy":-55.341944345},{"ecutrho":140,"k_density":0.1,"ecutwfc":25,"n_iterations":10,"time":101026,"converged":true,"accuracy":2.0e-10,"fermi":12.748,"total_energy":-55.338920335},{"ecutrho":140,"k_density":0.5,"ecutwfc":25,"n_iterations":16,"time":1032,"converged":true,"accuracy":2.1e-10,"fermi":12.5119,"total_energy":-55.332360295},{"ecutrho":140,"k_density":0.25,"ecutwfc":25,"n_iterations":11,"time":6091,"converged":true,"accuracy":9.7e-10,"fermi":12.8122,"total_energy":-55.3397542},{"ecutrho":140,"k_density":0.16666666666666666,"ecutwfc":25,"n_iterations":12,"time":26147,"converged":true,"accuracy":1.3e-10,"fermi":12.7273,"total_energy":-55.338313615},{"ecutrho":140,"k_density":0.125,"ecutwfc":25,"n_iterations":10,"time":49096,"converged":true,"accuracy":4.3e-10,"fermi":12.7729,"total_energy":-55.338986565},{"ecutrho":180,"k_density":0.1,"ecutwfc":25,"n_iterations":10,"time":101080,"converged":true,"accuracy":4.1e-10,"fermi":12.7471,"total_energy":-55.338635615},{"ecutrho":180,"k_density":0.5,"ecutwfc":25,"n_iterations":15,"time":1025,"converged":true,"accuracy":1.1e-10,"fermi":12.5111,"total_energy":-55.332074495},{"ecutrho":180,"k_density":0.25,"ecutwfc":25,"n_iterations":11,"time":6095,"converged":true,"accuracy":8.7e-10,"fermi":12.8113,"total_energy":-55.33947056},{"ecutrho":180,"k_density":0.16666666666666666,"ecutwfc":25,"n_iterations":12,"time":27081,"converged":true,"accuracy":1.8e-10,"fermi":12.7265,"total_energy":-55.338028645},{"ecutrho":180,"k_density":0.125,"ecutwfc":25,"n_iterations":10,"time":49076,"converged":true,"accuracy":4.2e-10,"fermi":12.7721,"total_energy":-55.33870183},{"ecutrho":220,"k_density":0.1,"ecutwfc":25,"n_iterations":10,"time":100104,"converged":true,"accuracy":3.2e-10,"fermi":12.7472,"total_energy":-55.33870023},{"ecutrho":220,"k_density":0.5,"ecutwfc":25,"n_iterations":17,"time":1045,"converged":true,"accuracy":3.4e-10,"fermi":12.5112,"total_energy":-55.332138155},{"ecutrho":220,"k_density":0.25,"ecutwfc":25,"n_iterations":11,"time":6089,"converged":true,"accuracy":8.8e-10,"fermi":12.8115,"total_energy":-55.33953512},{"ecutrho":220,"k_density":0.16666666666666666,"ecutwfc":25,"n_iterations":12,"time":27095,"converged":true,"accuracy":1.0e-10,"fermi":12.7266,"total_energy":-55.338093355},{"ecutrho":220,"k_density":0.125,"ecutwfc":25,"n_iterations":10,"time":49132,"converged":true,"accuracy":6.1e-10,"fermi":12.7722,"total_energy":-55.33876643},{"ecutrho":260,"k_density":0.1,"ecutwfc":25,"n_iterations":10,"time":100097,"converged":true,"accuracy":3.1e-10,"fermi":12.7471,"total_energy":-55.33869974},{"ecutrho":260,"k_density":0.5,"ecutwfc":25,"n_iterations":16,"time":1036,"converged":true,"accuracy":2.4e-11,"fermi":12.5111,"total_energy":-55.33213621},{"ecutrho":260,"k_density":0.25,"ecutwfc":25,"n_iterations":11,"time":6085,"converged":true,"accuracy":9.5e-10,"fermi":12.8113,"total_energy":-55.339535075},{"ecutrho":260,"k_density":0.16666666666666666,"ecutwfc":25,"n_iterations":12,"time":26168,"converged":true,"accuracy":1.3e-10,"fermi":12.7265,"total_energy":-55.338092875},{"ecutrho":260,"k_density":0.125,"ecutwfc":25,"n_iterations":10,"time":49120,"converged":true,"accuracy":5.2e-10,"fermi":12.772,"total_energy":-55.338765815},{"ecutrho":300,"k_density":0.1,"ecutwfc":25,"n_iterations":10,"time":101054,"converged":true,"accuracy":3.3e-10,"fermi":12.747,"total_energy":-55.338696425},{"ecutrho":300,"k_density":0.5,"ecutwfc":25,"n_iterations":15,"time":1027,"converged":true,"accuracy":1.4e-10,"fermi":12.5111,"total_energy":-55.33213242},{"ecutrho":300,"k_density":0.25,"ecutwfc":25,"n_iterations":11,"time":6091,"converged":true,"accuracy":9.3e-10,"fermi":12.8113,"total_energy":-55.3395319},{"ecutrho":300,"k_density":0.16666666666666666,"ecutwfc":25,"n_iterations":12,"time":26174,"converged":true,"accuracy":1.7e-10,"fermi":12.7264,"total_energy":-55.33808956},{"ecutrho":300,"k_density":0.125,"ecutwfc":25,"n_iterations":10,"time":49107,"converged":true,"accuracy":4.3e-10,"fermi":12.772,"total_energy":-55.338762455},{"ecutrho":340,"k_density":0.1,"ecutwfc":25,"n_iterations":10,"time":101037,"converged":true,"accuracy":3.3e-10,"fermi":12.747,"total_energy":-55.338702805},{"ecutrho":340,"k_density":0.5,"ecutwfc":25,"n_iterations":15,"time":1033,"converged":true,"accuracy":1.4e-10,"fermi":12.5111,"total_energy":-55.33213872},{"ecutrho":340,"k_density":0.25,"ecutwfc":25,"n_iterations":11,"time":6091,"converged":true,"accuracy":9.3e-10,"fermi":12.8113,"total_energy":-55.339538305},{"ecutrho":340,"k_density":0.16666666666666666,"ecutwfc":25,"n_iterations":12,"time":27129,"converged":true,"accuracy":1.6e-10,"fermi":12.7264,"total_energy":-55.33809594},{"ecutrho":340,"k_density":0.125,"ecutwfc":25,"n_iterations":10,"time":50070,"converged":true,"accuracy":4.2e-10,"fermi":12.772,"total_energy":-55.338768825},{"ecutrho":380,"k_density":0.1,"ecutwfc":25,"n_iterations":10,"time":100094,"converged":true,"accuracy":3.3e-10,"fermi":12.747,"total_energy":-55.33870133},{"ecutrho":380,"k_density":0.5,"ecutwfc":25,"n_iterations":15,"time":1032,"converged":true,"accuracy":3.1e-10,"fermi":12.5111,"total_energy":-55.332137465},{"ecutrho":380,"k_density":0.25,"ecutwfc":25,"n_iterations":11,"time":6087,"converged":true,"accuracy":9.4e-10,"fermi":12.8113,"total_energy":-55.339536755},{"ecutrho":380,"k_density":0.16666666666666666,"ecutwfc":25,"n_iterations":12,"time":27098,"converged":true,"accuracy":1.5e-10,"fermi":12.7264,"total_energy":-55.338094465},{"ecutrho":380,"k_density":0.125,"ecutwfc":25,"n_iterations":10,"time":49103,"converged":true,"accuracy":4.8e-10,"fermi":12.772,"total_energy":-55.338767375},{"ecutrho":100,"k_density":0.5,"ecutwfc":30,"n_iterations":18,"time":1051,"converged":true,"accuracy":3.4e-10,"fermi":12.5124,"total_energy":-55.343939335},{"ecutrho":100,"k_density":0.25,"ecutwfc":30,"n_iterations":14,"time":8067,"converged":true,"accuracy":1.7e-10,"fermi":12.815,"total_energy":-55.350711935},{"ecutrho":100,"k_density":0.16666666666666666,"ecutwfc":30,"n_iterations":12,"time":23091,"converged":true,"accuracy":3.3e-10,"fermi":12.7267,"total_energy":-55.34967914},{"ecutrho":100,"k_density":0.125,"ecutwfc":30,"n_iterations":10,"time":48088,"converged":true,"accuracy":8.8e-10,"fermi":12.7701,"total_energy":-55.350198335},{"ecutrho":140,"k_density":0.1,"ecutwfc":30,"n_iterations":13,"time":125031,"converged":true,"accuracy":3.2e-10,"fermi":12.7274,"total_energy":-55.34719968},{"ecutrho":140,"k_density":0.5,"ecutwfc":30,"n_iterations":14,"time":1022,"converged":true,"accuracy":3.4e-10,"fermi":12.4922,"total_energy":-55.34089607},{"ecutrho":140,"k_density":0.25,"ecutwfc":30,"n_iterations":14,"time":8078,"converged":true,"accuracy":1.4e-10,"fermi":12.7958,"total_energy":-55.34776155},{"ecutrho":140,"k_density":0.16666666666666666,"ecutwfc":30,"n_iterations":11,"time":22107,"converged":true,"accuracy":5.8e-10,"fermi":12.7074,"total_energy":-55.34671687},{"ecutrho":140,"k_density":0.125,"ecutwfc":30,"n_iterations":13,"time":64084,"converged":true,"accuracy":8.8e-11,"fermi":12.7507,"total_energy":-55.34723372},{"ecutrho":180,"k_density":0.1,"ecutwfc":30,"n_iterations":13,"time":125075,"converged":true,"accuracy":3.1e-10,"fermi":12.7265,"total_energy":-55.34693074},{"ecutrho":180,"k_density":0.5,"ecutwfc":30,"n_iterations":18,"time":1054,"converged":true,"accuracy":4.6e-10,"fermi":12.4915,"total_energy":-55.34062648},{"ecutrho":180,"k_density":0.25,"ecutwfc":30,"n_iterations":12,"time":7077,"converged":true,"accuracy":9.2e-10,"fermi":12.7951,"total_energy":-55.34749298},{"ecutrho":180,"k_density":0.16666666666666666,"ecutwfc":30,"n_iterations":11,"time":22098,"converged":true,"accuracy":7.6e-11,"fermi":12.7065,"total_energy":-55.346447945},{"ecutrho":180,"k_density":0.125,"ecutwfc":30,"n_iterations":13,"time":64108,"converged":true,"accuracy":7.1e-11,"fermi":12.7499,"total_energy":-55.34696474},{"ecutrho":220,"k_density":0.1,"ecutwfc":30,"n_iterations":13,"time":124059,"converged":true,"accuracy":3.2e-10,"fermi":12.7266,"total_energy":-55.346989485},{"ecutrho":220,"k_density":0.5,"ecutwfc":30,"n_iterations":18,"time":1053,"converged":true,"accuracy":3.6e-10,"fermi":12.4916,"total_energy":-55.34068413},{"ecutrho":220,"k_density":0.25,"ecutwfc":30,"n_iterations":12,"time":7084,"converged":true,"accuracy":8.9e-10,"fermi":12.7952,"total_energy":-55.34755195},{"ecutrho":220,"k_density":0.16666666666666666,"ecutwfc":30,"n_iterations":11,"time":22127,"converged":true,"accuracy":5.1e-10,"fermi":12.7066,"total_energy":-55.346506665},{"ecutrho":220,"k_density":0.125,"ecutwfc":30,"n_iterations":13,"time":64095,"converged":true,"accuracy":6.8e-11,"fermi":12.75,"total_energy":-55.34702348},{"ecutrho":260,"k_density":0.5,"ecutwfc":30,"n_iterations":18,"time":1062,"converged":true,"accuracy":4.2e-10,"fermi":12.4915,"total_energy":-55.340681855},{"ecutrho":260,"k_density":0.25,"ecutwfc":30,"n_iterations":12,"time":7111,"converged":true,"accuracy":9.1e-10,"fermi":12.795,"total_energy":-55.34755135},{"ecutrho":260,"k_density":0.16666666666666666,"ecutwfc":30,"n_iterations":11,"time":22131,"converged":true,"accuracy":4.9e-10,"fermi":12.7064,"total_energy":-55.34650568},{"ecutrho":260,"k_density":0.125,"ecutwfc":30,"n_iterations":13,"time":64093,"converged":true,"accuracy":5.4e-11,"fermi":12.7498,"total_energy":-55.347022375},{"ecutrho":300,"k_density":0.1,"ecutwfc":30,"n_iterations":13,"time":127060,"converged":true,"accuracy":2.5e-10,"fermi":12.7265,"total_energy":-55.346986105},{"ecutrho":300,"k_density":0.5,"ecutwfc":30,"n_iterations":17,"time":1050,"converged":true,"accuracy":6.6e-10,"fermi":12.4915,"total_energy":-55.340679145},{"ecutrho":300,"k_density":0.25,"ecutwfc":30,"n_iterations":12,"time":7099,"converged":true,"accuracy":9.4e-10,"fermi":12.795,"total_energy":-55.34754908},{"ecutrho":300,"k_density":0.16666666666666666,"ecutwfc":30,"n_iterations":11,"time":22122,"converged":true,"accuracy":6.6e-10,"fermi":12.7064,"total_energy":-55.34650331},{"ecutrho":300,"k_density":0.125,"ecutwfc":30,"n_iterations":13,"time":63167,"converged":true,"accuracy":6.0e-11,"fermi":12.7498,"total_energy":-55.347019955},{"ecutrho":340,"k_density":0.1,"ecutwfc":30,"n_iterations":13,"time":124116,"converged":true,"accuracy":2.7e-10,"fermi":12.7265,"total_energy":-55.34699223},{"ecutrho":340,"k_density":0.5,"ecutwfc":30,"n_iterations":17,"time":1052,"converged":true,"accuracy":6.6e-10,"fermi":12.4915,"total_energy":-55.340685195},{"ecutrho":340,"k_density":0.25,"ecutwfc":30,"n_iterations":12,"time":7093,"converged":true,"accuracy":9.1e-10,"fermi":12.795,"total_energy":-55.34755524},{"ecutrho":340,"k_density":0.16666666666666666,"ecutwfc":30,"n_iterations":11,"time":22117,"converged":true,"accuracy":6.2e-10,"fermi":12.7064,"total_energy":-55.346509435},{"ecutrho":380,"k_density":0.1,"ecutwfc":30,"n_iterations":13,"time":125047,"converged":true,"accuracy":2.9e-10,"fermi":12.7265,"total_energy":-55.346990495},{"ecutrho":380,"k_density":0.5,"ecutwfc":30,"n_iterations":17,"time":1060,"converged":true,"accuracy":6.7e-10,"fermi":12.4915,"total_energy":-55.3406836},{"ecutrho":380,"k_density":0.25,"ecutwfc":30,"n_iterations":12,"time":7097,"converged":true,"accuracy":9.4e-10,"fermi":12.795,"total_energy":-55.347553435},{"ecutrho":380,"k_density":0.16666666666666666,"ecutwfc":30,"n_iterations":11,"time":22121,"converged":true,"accuracy":5.4e-10,"fermi":12.7064,"total_energy":-55.346507695},{"ecutrho":380,"k_density":0.125,"ecutwfc":30,"n_iterations":13,"time":64166,"converged":true,"accuracy":7.5e-11,"fermi":12.7498,"total_energy":-55.34702436},{"ecutrho":100,"k_density":0.1,"ecutwfc":35,"n_iterations":12,"time":112085,"converged":true,"accuracy":2.0e-11,"fermi":12.7361,"total_energy":-55.352613625},{"ecutrho":100,"k_density":0.5,"ecutwfc":35,"n_iterations":17,"time":1047,"converged":true,"accuracy":1.1e-10,"fermi":12.507,"total_energy":-55.346318895},{"ecutrho":100,"k_density":0.25,"ecutwfc":35,"n_iterations":13,"time":8058,"converged":true,"accuracy":8.1e-11,"fermi":12.8053,"total_energy":-55.35308303},{"ecutrho":100,"k_density":0.16666666666666666,"ecutwfc":35,"n_iterations":11,"time":21126,"converged":true,"accuracy":5.5e-10,"fermi":12.7163,"total_energy":-55.35211349},{"ecutrho":100,"k_density":0.125,"ecutwfc":35,"n_iterations":13,"time":66114,"converged":true,"accuracy":1.9e-11,"fermi":12.7597,"total_energy":-55.35268342},{"ecutrho":140,"k_density":0.5,"ecutwfc":35,"n_iterations":19,"time":1059,"converged":true,"accuracy":4.3e-11,"fermi":12.4871,"total_energy":-55.34328982},{"ecutrho":140,"k_density":0.25,"ecutwfc":35,"n_iterations":14,"time":8081,"converged":true,"accuracy":7.3e-12,"fermi":12.7863,"total_energy":-55.350149475},{"ecutrho":140,"k_density":0.16666666666666666,"ecutwfc":35,"n_iterations":14,"time":26160,"converged":true,"accuracy":8.1e-10,"fermi":12.697,"total_energy":-55.349166945},{"ecutrho":140,"k_density":0.125,"ecutwfc":35,"n_iterations":13,"time":67113,"converged":true,"accuracy":7.8e-10,"fermi":12.7405,"total_energy":-55.3497349},{"ecutrho":180,"k_density":0.1,"ecutwfc":35,"n_iterations":12,"time":114063,"converged":true,"accuracy":8.6e-10,"fermi":12.7159,"total_energy":-55.349402045},{"ecutrho":180,"k_density":0.5,"ecutwfc":35,"n_iterations":18,"time":1052,"converged":true,"accuracy":8.1e-10,"fermi":12.4863,"total_energy":-55.34302523},{"ecutrho":180,"k_density":0.25,"ecutwfc":35,"n_iterations":15,"time":8120,"converged":true,"accuracy":4.8e-12,"fermi":12.7854,"total_energy":-55.349885825},{"ecutrho":180,"k_density":0.16666666666666666,"ecutwfc":35,"n_iterations":11,"time":21142,"converged":true,"accuracy":2.1e-10,"fermi":12.6962,"total_energy":-55.348903065},{"ecutrho":180,"k_density":0.125,"ecutwfc":35,"n_iterations":13,"time":67146,"converged":true,"accuracy":5.7e-10,"fermi":12.7396,"total_energy":-55.349471055},{"ecutrho":220,"k_density":0.5,"ecutwfc":35,"n_iterations":19,"time":1061,"converged":true,"accuracy":3.1e-11,"fermi":12.4864,"total_energy":-55.343080045},{"ecutrho":220,"k_density":0.25,"ecutwfc":35,"n_iterations":14,"time":8078,"converged":true,"accuracy":1.4e-11,"fermi":12.7856,"total_energy":-55.34994191},{"ecutrho":220,"k_density":0.16666666666666666,"ecutwfc":35,"n_iterations":16,"time":33165,"converged":true,"accuracy":4.5e-11,"fermi":12.6962,"total_energy":-55.34895888},{"ecutrho":220,"k_density":0.125,"ecutwfc":35,"n_iterations":13,"time":67097,"converged":true,"accuracy":5.2e-10,"fermi":12.7397,"total_energy":-55.34952685},{"ecutrho":260,"k_density":0.1,"ecutwfc":35,"n_iterations":12,"time":116114,"converged":true,"accuracy":9.7e-10,"fermi":12.7159,"total_energy":-55.3494566},{"ecutrho":260,"k_density":0.5,"ecutwfc":35,"n_iterations":20,"time":1068,"converged":true,"accuracy":5.7e-11,"fermi":12.4863,"total_energy":-55.34307754},{"ecutrho":260,"k_density":0.25,"ecutwfc":35,"n_iterations":14,"time":8071,"converged":true,"accuracy":1.0e-11,"fermi":12.7854,"total_energy":-55.34994103},{"ecutrho":260,"k_density":0.16666666666666666,"ecutwfc":35,"n_iterations":11,"time":21155,"converged":true,"accuracy":4.0e-10,"fermi":12.6961,"total_energy":-55.34895761},{"ecutrho":260,"k_density":0.125,"ecutwfc":35,"n_iterations":13,"time":67106,"converged":true,"accuracy":4.4e-10,"fermi":12.7396,"total_energy":-55.34952547},{"ecutrho":300,"k_density":0.1,"ecutwfc":35,"n_iterations":12,"time":113113,"converged":true,"accuracy":9.8e-10,"fermi":12.7159,"total_energy":-55.349454465},{"ecutrho":300,"k_density":0.5,"ecutwfc":35,"n_iterations":19,"time":1072,"converged":true,"accuracy":1.0e-10,"fermi":12.4862,"total_energy":-55.34307512},{"ecutrho":300,"k_density":0.25,"ecutwfc":35,"n_iterations":14,"time":8077,"converged":true,"accuracy":1.8e-11,"fermi":12.7854,"total_energy":-55.34993901},{"ecutrho":300,"k_density":0.16666666666666666,"ecutwfc":35,"n_iterations":11,"time":21129,"converged":true,"accuracy":3.9e-10,"fermi":12.6961,"total_energy":-55.348955485},{"ecutrho":300,"k_density":0.125,"ecutwfc":35,"n_iterations":13,"time":68141,"converged":true,"accuracy":2.7e-10,"fermi":12.7395,"total_energy":-55.3495233},{"ecutrho":340,"k_density":0.1,"ecutwfc":35,"n_iterations":12,"time":114036,"converged":true,"accuracy":1.0e-9,"fermi":12.7159,"total_energy":-55.34946046},{"ecutrho":340,"k_density":0.5,"ecutwfc":35,"n_iterations":19,"time":1079,"converged":true,"accuracy":1.0e-10,"fermi":12.4862,"total_energy":-55.343081045},{"ecutrho":340,"k_density":0.25,"ecutwfc":35,"n_iterations":14,"time":8080,"converged":true,"accuracy":1.9e-11,"fermi":12.7854,"total_energy":-55.349945045},{"ecutrho":340,"k_density":0.16666666666666666,"ecutwfc":35,"n_iterations":11,"time":22089,"converged":true,"accuracy":5.0e-10,"fermi":12.6961,"total_energy":-55.34896148},{"ecutrho":340,"k_density":0.125,"ecutwfc":35,"n_iterations":13,"time":68104,"converged":true,"accuracy":2.8e-10,"fermi":12.7395,"total_energy":-55.349529285},{"ecutrho":380,"k_density":0.1,"ecutwfc":35,"n_iterations":13,"time":131082,"converged":true,"accuracy":2.7e-11,"fermi":12.7159,"total_energy":-55.349458685},{"ecutrho":380,"k_density":0.5,"ecutwfc":35,"n_iterations":18,"time":1068,"converged":true,"accuracy":9.2e-10,"fermi":12.4863,"total_energy":-55.34307939},{"ecutrho":380,"k_density":0.25,"ecutwfc":35,"n_iterations":18,"time":10068,"converged":true,"accuracy":4.4e-11,"fermi":12.7854,"total_energy":-55.349943195},{"ecutrho":380,"k_density":0.16666666666666666,"ecutwfc":35,"n_iterations":11,"time":21143,"converged":true,"accuracy":5.4e-10,"fermi":12.6961,"total_energy":-55.3489597},{"ecutrho":380,"k_density":0.125,"ecutwfc":35,"n_iterations":13,"time":68109,"converged":true,"accuracy":2.9e-10,"fermi":12.7395,"total_energy":-55.349527525},{"ecutrho":100,"k_density":0.5,"ecutwfc":40,"n_iterations":17,"time":1052,"converged":true,"accuracy":1.8e-10,"fermi":12.5035,"total_energy":-55.34715735},{"ecutrho":100,"k_density":0.25,"ecutwfc":40,"n_iterations":14,"time":8097,"converged":true,"accuracy":1.2e-10,"fermi":12.8029,"total_energy":-55.35385791},{"ecutrho":100,"k_density":0.16666666666666666,"ecutwfc":40,"n_iterations":15,"time":30098,"converged":true,"accuracy":1.7e-11,"fermi":12.7131,"total_energy":-55.35289389},{"ecutrho":100,"k_density":0.125,"ecutwfc":40,"n_iterations":12,"time":68111,"converged":true,"accuracy":2.9e-10,"fermi":12.7564,"total_energy":-55.35347044},{"ecutrho":140,"k_density":0.1,"ecutwfc":40,"n_iterations":13,"time":133116,"converged":true,"accuracy":3.5e-10,"fermi":12.7137,"total_energy":-55.35045175},{"ecutrho":140,"k_density":0.5,"ecutwfc":40,"n_iterations":18,"time":1072,"converged":true,"accuracy":2.0e-11,"fermi":12.4836,"total_energy":-55.344130025},{"ecutrho":140,"k_density":0.25,"ecutwfc":40,"n_iterations":13,"time":8066,"converged":true,"accuracy":7.7e-10,"fermi":12.7839,"total_energy":-55.350925145},{"ecutrho":140,"k_density":0.16666666666666666,"ecutwfc":40,"n_iterations":14,"time":28120,"converged":true,"accuracy":5.7e-11,"fermi":12.6939,"total_energy":-55.34994777},{"ecutrho":140,"k_density":0.125,"ecutwfc":40,"n_iterations":10,"time":57129,"converged":true,"accuracy":7.8e-10,"fermi":12.7373,"total_energy":-55.350522515},{"ecutrho":180,"k_density":0.1,"ecutwfc":40,"n_iterations":12,"time":131107,"converged":true,"accuracy":1.1e-10,"fermi":12.7128,"total_energy":-55.35018991},{"ecutrho":180,"k_density":0.5,"ecutwfc":40,"n_iterations":18,"time":1060,"converged":true,"accuracy":1.9e-12,"fermi":12.4828,"total_energy":-55.34386738},{"ecutrho":180,"k_density":0.25,"ecutwfc":40,"n_iterations":13,"time":8070,"converged":true,"accuracy":2.0e-10,"fermi":12.7831,"total_energy":-55.350663485},{"ecutrho":180,"k_density":0.16666666666666666,"ecutwfc":40,"n_iterations":14,"time":28146,"converged":true,"accuracy":1.6e-10,"fermi":12.693,"total_energy":-55.34968591},{"ecutrho":180,"k_density":0.125,"ecutwfc":40,"n_iterations":10,"time":59022,"converged":true,"accuracy":9.3e-10,"fermi":12.7365,"total_energy":-55.350260715},{"ecutrho":220,"k_density":0.1,"ecutwfc":40,"n_iterations":12,"time":128059,"converged":true,"accuracy":4.7e-10,"fermi":12.713,"total_energy":-55.350244495},{"ecutrho":220,"k_density":0.5,"ecutwfc":40,"n_iterations":18,"time":1062,"converged":true,"accuracy":1.6e-12,"fermi":12.4829,"total_energy":-55.34392093},{"ecutrho":220,"k_density":0.25,"ecutwfc":40,"n_iterations":14,"time":8119,"converged":true,"accuracy":4.8e-10,"fermi":12.7832,"total_energy":-55.350718375},{"ecutrho":220,"k_density":0.16666666666666666,"ecutwfc":40,"n_iterations":14,"time":28143,"converged":true,"accuracy":4.4e-10,"fermi":12.6932,"total_energy":-55.349740495},{"ecutrho":220,"k_density":0.125,"ecutwfc":40,"n_iterations":10,"time":58097,"converged":true,"accuracy":9.5e-10,"fermi":12.7366,"total_energy":-55.350315265},{"ecutrho":260,"k_density":0.1,"ecutwfc":40,"n_iterations":12,"time":128107,"converged":true,"accuracy":6.5e-10,"fermi":12.7129,"total_energy":-55.350243055},{"ecutrho":260,"k_density":0.5,"ecutwfc":40,"n_iterations":18,"time":1067,"converged":true,"accuracy":3.2e-12,"fermi":12.4828,"total_energy":-55.34391828},{"ecutrho":260,"k_density":0.25,"ecutwfc":40,"n_iterations":14,"time":8120,"converged":true,"accuracy":2.0e-11,"fermi":12.783,"total_energy":-55.350717315},{"ecutrho":260,"k_density":0.16666666666666666,"ecutwfc":40,"n_iterations":14,"time":28151,"converged":true,"accuracy":2.3e-11,"fermi":12.693,"total_energy":-55.34973906},{"ecutrho":260,"k_density":0.125,"ecutwfc":40,"n_iterations":10,"time":57159,"converged":true,"accuracy":8.7e-10,"fermi":12.7364,"total_energy":-55.350313725},{"ecutrho":300,"k_density":0.1,"ecutwfc":40,"n_iterations":12,"time":128055,"converged":true,"accuracy":6.9e-10,"fermi":12.7128,"total_energy":-55.35024085},{"ecutrho":300,"k_density":0.5,"ecutwfc":40,"n_iterations":18,"time":1072,"converged":true,"accuracy":1.2e-11,"fermi":12.4828,"total_energy":-55.34391581},{"ecutrho":300,"k_density":0.25,"ecutwfc":40,"n_iterations":14,"time":8111,"converged":true,"accuracy":9.2e-11,"fermi":12.783,"total_energy":-55.35071519},{"ecutrho":300,"k_density":0.16666666666666666,"ecutwfc":40,"n_iterations":13,"time":27099,"converged":true,"accuracy":9.0e-10,"fermi":12.6931,"total_energy":-55.349736865},{"ecutrho":300,"k_density":0.125,"ecutwfc":40,"n_iterations":10,"time":58080,"converged":true,"accuracy":8.9e-10,"fermi":12.7364,"total_energy":-55.350311485},{"ecutrho":340,"k_density":0.1,"ecutwfc":40,"n_iterations":12,"time":127084,"converged":true,"accuracy":6.8e-10,"fermi":12.7128,"total_energy":-55.350246775},{"ecutrho":340,"k_density":0.5,"ecutwfc":40,"n_iterations":18,"time":1074,"converged":true,"accuracy":1.3e-11,"fermi":12.4828,"total_energy":-55.343921665},{"ecutrho":340,"k_density":0.25,"ecutwfc":40,"n_iterations":13,"time":8085,"converged":true,"accuracy":9.1e-10,"fermi":12.783,"total_energy":-55.350721155},{"ecutrho":340,"k_density":0.16666666666666666,"ecutwfc":40,"n_iterations":13,"time":27107,"converged":true,"accuracy":9.0e-10,"fermi":12.6931,"total_energy":-55.349742785},{"ecutrho":340,"k_density":0.125,"ecutwfc":40,"n_iterations":10,"time":58113,"converged":true,"accuracy":8.8e-10,"fermi":12.7364,"total_energy":-55.350317395},{"ecutrho":380,"k_density":0.1,"ecutwfc":40,"n_iterations":12,"time":127068,"converged":true,"accuracy":6.6e-10,"fermi":12.7128,"total_energy":-55.35024505},{"ecutrho":380,"k_density":0.5,"ecutwfc":40,"n_iterations":18,"time":1076,"converged":true,"accuracy":6.1e-12,"fermi":12.4828,"total_energy":-55.34392006},{"ecutrho":380,"k_density":0.25,"ecutwfc":40,"n_iterations":13,"time":8078,"converged":true,"accuracy":9.0e-10,"fermi":12.783,"total_energy":-55.35071937},{"ecutrho":380,"k_density":0.16666666666666666,"ecutwfc":40,"n_iterations":13,"time":27100,"converged":true,"accuracy":9.1e-10,"fermi":12.6931,"total_energy":-55.34974106},{"ecutrho":380,"k_density":0.125,"ecutwfc":40,"n_iterations":10,"time":58119,"converged":true,"accuracy":8.8e-10,"fermi":12.7364,"total_energy":-55.350315695},{"ecutrho":100,"k_density":0.1,"ecutwfc":45,"n_iterations":13,"time":136053,"converged":true,"accuracy":2.0e-10,"fermi":12.7315,"total_energy":-55.353587665},{"ecutrho":100,"k_density":0.5,"ecutwfc":45,"n_iterations":18,"time":1061,"converged":true,"accuracy":2.8e-10,"fermi":12.5019,"total_energy":-55.34736415},{"ecutrho":100,"k_density":0.25,"ecutwfc":45,"n_iterations":11,"time":7069,"converged":true,"accuracy":4.4e-10,"fermi":12.8011,"total_energy":-55.3540481},{"ecutrho":100,"k_density":0.16666666666666666,"ecutwfc":45,"n_iterations":13,"time":28097,"converged":true,"accuracy":8.2e-11,"fermi":12.7117,"total_energy":-55.35308198},{"ecutrho":100,"k_density":0.125,"ecutwfc":45,"n_iterations":15,"time":79109,"converged":true,"accuracy":5.3e-10,"fermi":12.755,"total_energy":-55.353661675},{"ecutrho":140,"k_density":0.1,"ecutwfc":45,"n_iterations":13,"time":148105,"converged":true,"accuracy":9.4e-10,"fermi":12.7124,"total_energy":-55.35064012},{"ecutrho":140,"k_density":0.5,"ecutwfc":45,"n_iterations":18,"time":1068,"converged":true,"accuracy":3.4e-11,"fermi":12.482,"total_energy":-55.34433586},{"ecutrho":140,"k_density":0.25,"ecutwfc":45,"n_iterations":11,"time":7071,"converged":true,"accuracy":4.8e-10,"fermi":12.7822,"total_energy":-55.351114765},{"ecutrho":140,"k_density":0.125,"ecutwfc":45,"n_iterations":12,"time":68099,"converged":true,"accuracy":5.0e-10,"fermi":12.7359,"total_energy":-55.350713295},{"ecutrho":180,"k_density":0.1,"ecutwfc":45,"n_iterations":13,"time":148056,"converged":true,"accuracy":4.4e-10,"fermi":12.7115,"total_energy":-55.350378275},{"ecutrho":180,"k_density":0.5,"ecutwfc":45,"n_iterations":22,"time":1092,"converged":true,"accuracy":1.2e-10,"fermi":12.4813,"total_energy":-55.34407338},{"ecutrho":180,"k_density":0.25,"ecutwfc":45,"n_iterations":11,"time":7091,"converged":true,"accuracy":6.7e-10,"fermi":12.7813,"total_energy":-55.3508531},{"ecutrho":180,"k_density":0.16666666666666666,"ecutwfc":45,"n_iterations":12,"time":27105,"converged":true,"accuracy":9.2e-10,"fermi":12.6917,"total_energy":-55.349873665},{"ecutrho":180,"k_density":0.125,"ecutwfc":45,"n_iterations":12,"time":68109,"converged":true,"accuracy":5.2e-10,"fermi":12.735,"total_energy":-55.3504515},{"ecutrho":220,"k_density":0.1,"ecutwfc":45,"n_iterations":13,"time":151115,"converged":true,"accuracy":8.1e-10,"fermi":12.7116,"total_energy":-55.35043297},{"ecutrho":220,"k_density":0.5,"ecutwfc":45,"n_iterations":23,"time":1098,"converged":true,"accuracy":8.5e-10,"fermi":12.4814,"total_energy":-55.344127035},{"ecutrho":220,"k_density":0.25,"ecutwfc":45,"n_iterations":11,"time":7089,"converged":true,"accuracy":5.9e-10,"fermi":12.7815,"total_energy":-55.350908095},{"ecutrho":220,"k_density":0.16666666666666666,"ecutwfc":45,"n_iterations":13,"time":29097,"converged":true,"accuracy":2.4e-10,"fermi":12.6918,"total_energy":-55.34992836},{"ecutrho":220,"k_density":0.125,"ecutwfc":45,"n_iterations":12,"time":68176,"converged":true,"accuracy":4.9e-10,"fermi":12.7351,"total_energy":-55.350506155},{"ecutrho":260,"k_density":0.1,"ecutwfc":45,"n_iterations":13,"time":149132,"converged":true,"accuracy":7.1e-10,"fermi":12.7115,"total_energy":-55.350431415},{"ecutrho":260,"k_density":0.5,"ecutwfc":45,"n_iterations":22,"time":1092,"converged":true,"accuracy":5.9e-10,"fermi":12.4812,"total_energy":-55.344124205},{"ecutrho":260,"k_density":0.25,"ecutwfc":45,"n_iterations":11,"time":7085,"converged":true,"accuracy":5.8e-10,"fermi":12.7813,"total_energy":-55.350906925},{"ecutrho":260,"k_density":0.16666666666666666,"ecutwfc":45,"n_iterations":13,"time":29147,"converged":true,"accuracy":1.9e-10,"fermi":12.6917,"total_energy":-55.34992681},{"ecutrho":260,"k_density":0.125,"ecutwfc":45,"n_iterations":12,"time":69134,"converged":true,"accuracy":4.9e-10,"fermi":12.735,"total_energy":-55.350504495},{"ecutrho":300,"k_density":0.5,"ecutwfc":45,"n_iterations":22,"time":1093,"converged":true,"accuracy":8.6e-10,"fermi":12.4812,"total_energy":-55.3441216},{"ecutrho":300,"k_density":0.25,"ecutwfc":45,"n_iterations":11,"time":7130,"converged":true,"accuracy":5.4e-10,"fermi":12.7813,"total_energy":-55.35090471},{"ecutrho":300,"k_density":0.16666666666666666,"ecutwfc":45,"n_iterations":13,"time":29106,"converged":true,"accuracy":1.7e-10,"fermi":12.6916,"total_energy":-55.349924515},{"ecutrho":300,"k_density":0.125,"ecutwfc":45,"n_iterations":12,"time":69107,"converged":true,"accuracy":4.7e-10,"fermi":12.735,"total_energy":-55.350502165},{"ecutrho":340,"k_density":0.1,"ecutwfc":45,"n_iterations":13,"time":150068,"converged":true,"accuracy":6.4e-10,"fermi":12.7114,"total_energy":-55.35043503},{"ecutrho":340,"k_density":0.5,"ecutwfc":45,"n_iterations":23,"time":1109,"converged":true,"accuracy":5.8e-10,"fermi":12.4812,"total_energy":-55.34412744},{"ecutrho":340,"k_density":0.25,"ecutwfc":45,"n_iterations":11,"time":7100,"converged":true,"accuracy":5.5e-10,"fermi":12.7813,"total_energy":-55.35091066},{"ecutrho":340,"k_density":0.16666666666666666,"ecutwfc":45,"n_iterations":13,"time":29107,"converged":true,"accuracy":1.6e-10,"fermi":12.6916,"total_energy":-55.349930425},{"ecutrho":340,"k_density":0.125,"ecutwfc":45,"n_iterations":12,"time":69150,"converged":true,"accuracy":4.7e-10,"fermi":12.735,"total_energy":-55.350508065},{"ecutrho":380,"k_density":0.1,"ecutwfc":45,"n_iterations":13,"time":151082,"converged":true,"accuracy":6.5e-10,"fermi":12.7115,"total_energy":-55.350433335},{"ecutrho":380,"k_density":0.5,"ecutwfc":45,"n_iterations":22,"time":1100,"converged":true,"accuracy":4.9e-10,"fermi":12.4812,"total_energy":-55.34412589},{"ecutrho":380,"k_density":0.25,"ecutwfc":45,"n_iterations":11,"time":7092,"converged":true,"accuracy":5.8e-10,"fermi":12.7813,"total_energy":-55.350908905},{"ecutrho":380,"k_density":0.16666666666666666,"ecutwfc":45,"n_iterations":12,"time":27099,"converged":true,"accuracy":8.1e-10,"fermi":12.6917,"total_energy":-55.349928735},{"ecutrho":380,"k_density":0.125,"ecutwfc":45,"n_iterations":12,"time":68182,"converged":true,"accuracy":4.8e-10,"fermi":12.735,"total_energy":-55.35050639},{"ecutrho":100,"k_density":0.1,"ecutwfc":50,"n_iterations":13,"time":141056,"converged":true,"accuracy":2.8e-10,"fermi":12.7312,"total_energy":-55.353648635},{"ecutrho":100,"k_density":0.5,"ecutwfc":50,"n_iterations":17,"time":1049,"converged":true,"accuracy":4.6e-12,"fermi":12.5015,"total_energy":-55.34742947},{"ecutrho":100,"k_density":0.25,"ecutwfc":50,"n_iterations":11,"time":7068,"converged":true,"accuracy":2.1e-10,"fermi":12.8008,"total_energy":-55.354107035},{"ecutrho":100,"k_density":0.16666666666666666,"ecutwfc":50,"n_iterations":11,"time":25105,"converged":true,"accuracy":7.5e-10,"fermi":12.7115,"total_energy":-55.353143605},{"ecutrho":100,"k_density":0.125,"ecutwfc":50,"n_iterations":11,"time":65083,"converged":true,"accuracy":7.9e-10,"fermi":12.7548,"total_energy":-55.35372291},{"ecutrho":140,"k_density":0.1,"ecutwfc":50,"n_iterations":11,"time":127046,"converged":true,"accuracy":5.5e-10,"fermi":12.712,"total_energy":-55.35070332},{"ecutrho":140,"k_density":0.5,"ecutwfc":50,"n_iterations":16,"time":1044,"converged":true,"accuracy":6.1e-10,"fermi":12.4817,"total_energy":-55.34440327},{"ecutrho":140,"k_density":0.25,"ecutwfc":50,"n_iterations":13,"time":8070,"converged":true,"accuracy":3.4e-10,"fermi":12.7818,"total_energy":-55.351176195},{"ecutrho":140,"k_density":0.16666666666666666,"ecutwfc":50,"n_iterations":13,"time":29150,"converged":true,"accuracy":4.2e-10,"fermi":12.6923,"total_energy":-55.350199345},{"ecutrho":140,"k_density":0.125,"ecutwfc":50,"n_iterations":10,"time":61148,"converged":true,"accuracy":8.8e-10,"fermi":12.7357,"total_energy":-55.35077674},{"ecutrho":180,"k_density":0.1,"ecutwfc":50,"n_iterations":11,"time":127135,"converged":true,"accuracy":2.7e-11,"fermi":12.7112,"total_energy":-55.350440665},{"ecutrho":180,"k_density":0.5,"ecutwfc":50,"n_iterations":17,"time":1052,"converged":true,"accuracy":3.6e-10,"fermi":12.4809,"total_energy":-55.34414002},{"ecutrho":180,"k_density":0.25,"ecutwfc":50,"n_iterations":13,"time":8083,"converged":true,"accuracy":6.1e-12,"fermi":12.781,"total_energy":-55.350913745},{"ecutrho":180,"k_density":0.16666666666666666,"ecutwfc":50,"n_iterations":13,"time":30137,"converged":true,"accuracy":4.2e-10,"fermi":12.6915,"total_energy":-55.349936685},{"ecutrho":180,"k_density":0.125,"ecutwfc":50,"n_iterations":10,"time":61108,"converged":true,"accuracy":7.9e-10,"fermi":12.7348,"total_energy":-55.350514145},{"ecutrho":220,"k_density":0.1,"ecutwfc":50,"n_iterations":11,"time":129127,"converged":true,"accuracy":2.9e-11,"fermi":12.7114,"total_energy":-55.350495645},{"ecutrho":220,"k_density":0.5,"ecutwfc":50,"n_iterations":22,"time":1100,"converged":true,"accuracy":8.3e-11,"fermi":12.481,"total_energy":-55.344193965},{"ecutrho":220,"k_density":0.25,"ecutwfc":50,"n_iterations":11,"time":7101,"converged":true,"accuracy":7.1e-10,"fermi":12.7811,"total_energy":-55.350969015},{"ecutrho":220,"k_density":0.16666666666666666,"ecutwfc":50,"n_iterations":13,"time":30155,"converged":true,"accuracy":4.1e-10,"fermi":12.6916,"total_energy":-55.349991655},{"ecutrho":220,"k_density":0.125,"ecutwfc":50,"n_iterations":10,"time":63116,"converged":true,"accuracy":9.0e-10,"fermi":12.7349,"total_energy":-55.350569085},{"ecutrho":260,"k_density":0.5,"ecutwfc":50,"n_iterations":21,"time":1095,"converged":true,"accuracy":8.1e-10,"fermi":12.4809,"total_energy":-55.344191165},{"ecutrho":260,"k_density":0.25,"ecutwfc":50,"n_iterations":11,"time":7089,"converged":true,"accuracy":5.6e-10,"fermi":12.781,"total_energy":-55.35096787},{"ecutrho":260,"k_density":0.16666666666666666,"ecutwfc":50,"n_iterations":13,"time":30142,"converged":true,"accuracy":4.2e-10,"fermi":12.6915,"total_energy":-55.34999013},{"ecutrho":260,"k_density":0.125,"ecutwfc":50,"n_iterations":10,"time":62158,"converged":true,"accuracy":8.4e-10,"fermi":12.7348,"total_energy":-55.350567445},{"ecutrho":300,"k_density":0.1,"ecutwfc":50,"n_iterations":11,"time":132132,"converged":true,"accuracy":4.3e-11,"fermi":12.7112,"total_energy":-55.35049176},{"ecutrho":300,"k_density":0.5,"ecutwfc":50,"n_iterations":18,"time":1080,"converged":true,"accuracy":1.9e-10,"fermi":12.4809,"total_energy":-55.34418851},{"ecutrho":300,"k_density":0.25,"ecutwfc":50,"n_iterations":13,"time":8121,"converged":true,"accuracy":9.7e-11,"fermi":12.7809,"total_energy":-55.35096561},{"ecutrho":300,"k_density":0.16666666666666666,"ecutwfc":50,"n_iterations":13,"time":30141,"converged":true,"accuracy":4.1e-10,"fermi":12.6914,"total_energy":-55.349987785},{"ecutrho":300,"k_density":0.125,"ecutwfc":50,"n_iterations":10,"time":62177,"converged":true,"accuracy":8.4e-10,"fermi":12.7347,"total_energy":-55.35056506},{"ecutrho":340,"k_density":0.1,"ecutwfc":50,"n_iterations":11,"time":131070,"converged":true,"accuracy":4.3e-11,"fermi":12.7112,"total_energy":-55.35049767},{"ecutrho":340,"k_density":0.5,"ecutwfc":50,"n_iterations":18,"time":1076,"converged":true,"accuracy":1.7e-10,"fermi":12.4809,"total_energy":-55.34419436},{"ecutrho":340,"k_density":0.25,"ecutwfc":50,"n_iterations":13,"time":8111,"converged":true,"accuracy":1.5e-10,"fermi":12.7809,"total_energy":-55.35097156},{"ecutrho":340,"k_density":0.16666666666666666,"ecutwfc":50,"n_iterations":13,"time":30138,"converged":true,"accuracy":4.2e-10,"fermi":12.6914,"total_energy":-55.3499937},{"ecutrho":340,"k_density":0.125,"ecutwfc":50,"n_iterations":10,"time":62101,"converged":true,"accuracy":8.2e-10,"fermi":12.7348,"total_energy":-55.35057096},{"ecutrho":380,"k_density":0.1,"ecutwfc":50,"n_iterations":11,"time":130096,"converged":true,"accuracy":5.0e-11,"fermi":12.7112,"total_energy":-55.35049599},{"ecutrho":380,"k_density":0.5,"ecutwfc":50,"n_iterations":21,"time":1102,"converged":true,"accuracy":2.6e-10,"fermi":12.4808,"total_energy":-55.34419281},{"ecutrho":380,"k_density":0.25,"ecutwfc":50,"n_iterations":13,"time":8106,"converged":true,"accuracy":1.5e-10,"fermi":12.7809,"total_energy":-55.350969815},{"ecutrho":380,"k_density":0.16666666666666666,"ecutwfc":50,"n_iterations":13,"time":30179,"converged":true,"accuracy":4.1e-10,"fermi":12.6914,"total_energy":-55.349992015},{"ecutrho":380,"k_density":0.125,"ecutwfc":50,"n_iterations":10,"time":62138,"converged":true,"accuracy":8.2e-10,"fermi":12.7348,"total_energy":-55.3505693},{"ecutrho":100,"k_density":0.1,"ecutwfc":55,"n_iterations":13,"time":141115,"converged":true,"accuracy":3.1e-10,"fermi":12.7313,"total_energy":-55.35373032},{"ecutrho":100,"k_density":0.5,"ecutwfc":55,"n_iterations":19,"time":1069,"converged":true,"accuracy":1.5e-10,"fermi":12.5015,"total_energy":-55.347498225},{"ecutrho":100,"k_density":0.25,"ecutwfc":55,"n_iterations":13,"time":8084,"converged":true,"accuracy":2.5e-11,"fermi":12.8008,"total_energy":-55.35418888},{"ecutrho":100,"k_density":0.16666666666666666,"ecutwfc":55,"n_iterations":13,"time":30096,"converged":true,"accuracy":8.0e-10,"fermi":12.7114,"total_energy":-55.353224065},{"ecutrho":140,"k_density":0.5,"ecutwfc":55,"n_iterations":16,"time":1050,"converged":true,"accuracy":5.4e-10,"fermi":12.4817,"total_energy":-55.34447116},{"ecutrho":140,"k_density":0.25,"ecutwfc":55,"n_iterations":13,"time":8065,"converged":true,"accuracy":6.7e-11,"fermi":12.7818,"total_energy":-55.35125681},{"ecutrho":140,"k_density":0.16666666666666666,"ecutwfc":55,"n_iterations":12,"time":28103,"converged":true,"accuracy":8.4e-11,"fermi":12.6923,"total_energy":-55.35027835},{"ecutrho":140,"k_density":0.125,"ecutwfc":55,"n_iterations":11,"time":67148,"converged":true,"accuracy":4.0e-10,"fermi":12.7356,"total_energy":-55.350857455},{"ecutrho":180,"k_density":0.1,"ecutwfc":55,"n_iterations":12,"time":141051,"converged":true,"accuracy":6.3e-10,"fermi":12.7113,"total_energy":-55.350520285},{"ecutrho":180,"k_density":0.5,"ecutwfc":55,"n_iterations":14,"time":1035,"converged":true,"accuracy":6.3e-10,"fermi":12.4809,"total_energy":-55.344207325},{"ecutrho":180,"k_density":0.25,"ecutwfc":55,"n_iterations":14,"time":9074,"converged":true,"accuracy":4.3e-10,"fermi":12.781,"total_energy":-55.350993765},{"ecutrho":180,"k_density":0.16666666666666666,"ecutwfc":55,"n_iterations":12,"time":28172,"converged":true,"accuracy":1.9e-10,"fermi":12.6915,"total_energy":-55.35001512},{"ecutrho":220,"k_density":0.5,"ecutwfc":55,"n_iterations":19,"time":1079,"converged":true,"accuracy":3.6e-10,"fermi":12.481,"total_energy":-55.34426128},{"ecutrho":220,"k_density":0.25,"ecutwfc":55,"n_iterations":13,"time":8112,"converged":true,"accuracy":1.4e-11,"fermi":12.7811,"total_energy":-55.35104899},{"ecutrho":220,"k_density":0.16666666666666666,"ecutwfc":55,"n_iterations":12,"time":29123,"converged":true,"accuracy":1.2e-10,"fermi":12.6916,"total_energy":-55.35007006},{"ecutrho":220,"k_density":0.125,"ecutwfc":55,"n_iterations":11,"time":69150,"converged":true,"accuracy":5.0e-10,"fermi":12.7349,"total_energy":-55.350649195},{"ecutrho":260,"k_density":0.1,"ecutwfc":55,"n_iterations":12,"time":145080,"converged":true,"accuracy":6.3e-10,"fermi":12.7113,"total_energy":-55.350573875},{"ecutrho":260,"k_density":0.5,"ecutwfc":55,"n_iterations":19,"time":1088,"converged":true,"accuracy":3.1e-10,"fermi":12.4809,"total_energy":-55.344258635},{"ecutrho":260,"k_density":0.25,"ecutwfc":55,"n_iterations":13,"time":8112,"converged":true,"accuracy":5.8e-11,"fermi":12.781,"total_energy":-55.35104804},{"ecutrho":260,"k_density":0.16666666666666666,"ecutwfc":55,"n_iterations":12,"time":29087,"converged":true,"accuracy":7.0e-11,"fermi":12.6915,"total_energy":-55.35006872},{"ecutrho":260,"k_density":0.125,"ecutwfc":55,"n_iterations":11,"time":69093,"converged":true,"accuracy":4.9e-10,"fermi":12.7347,"total_energy":-55.35064774},{"ecutrho":300,"k_density":0.1,"ecutwfc":55,"n_iterations":12,"time":143074,"converged":true,"accuracy":6.1e-10,"fermi":12.7112,"total_energy":-55.35057155},{"ecutrho":300,"k_density":0.5,"ecutwfc":55,"n_iterations":19,"time":1082,"converged":true,"accuracy":4.0e-12,"fermi":12.4808,"total_energy":-55.344255995},{"ecutrho":300,"k_density":0.25,"ecutwfc":55,"n_iterations":13,"time":8102,"converged":true,"accuracy":2.5e-10,"fermi":12.7809,"total_energy":-55.351045805},{"ecutrho":300,"k_density":0.16666666666666666,"ecutwfc":55,"n_iterations":12,"time":29140,"converged":true,"accuracy":1.2e-10,"fermi":12.6914,"total_energy":-55.350066395},{"ecutrho":300,"k_density":0.125,"ecutwfc":55,"n_iterations":11,"time":69129,"converged":true,"accuracy":5.5e-10,"fermi":12.7347,"total_energy":-55.35064538},{"ecutrho":340,"k_density":0.1,"ecutwfc":55,"n_iterations":12,"time":142109,"converged":true,"accuracy":6.1e-10,"fermi":12.7112,"total_energy":-55.35057746},{"ecutrho":340,"k_density":0.5,"ecutwfc":55,"n_iterations":19,"time":1086,"converged":true,"accuracy":3.4e-11,"fermi":12.4808,"total_energy":-55.34426184},{"ecutrho":340,"k_density":0.25,"ecutwfc":55,"n_iterations":13,"time":8107,"converged":true,"accuracy":6.0e-10,"fermi":12.781,"total_energy":-55.35105175},{"ecutrho":340,"k_density":0.16666666666666666,"ecutwfc":55,"n_iterations":12,"time":29091,"converged":true,"accuracy":1.2e-10,"fermi":12.6914,"total_energy":-55.350072305},{"ecutrho":340,"k_density":0.125,"ecutwfc":55,"n_iterations":11,"time":69181,"converged":true,"accuracy":5.4e-10,"fermi":12.7347,"total_energy":-55.350651275},{"ecutrho":380,"k_density":0.1,"ecutwfc":55,"n_iterations":12,"time":144063,"converged":true,"accuracy":6.2e-10,"fermi":12.7112,"total_energy":-55.35057576},{"ecutrho":380,"k_density":0.5,"ecutwfc":55,"n_iterations":19,"time":1088,"converged":true,"accuracy":4.1e-11,"fermi":12.4808,"total_energy":-55.34426028},{"ecutrho":380,"k_density":0.25,"ecutwfc":55,"n_iterations":13,"time":8107,"converged":true,"accuracy":2.4e-10,"fermi":12.781,"total_energy":-55.35104999},{"ecutrho":380,"k_density":0.16666666666666666,"ecutwfc":55,"n_iterations":12,"time":29162,"converged":true,"accuracy":1.2e-10,"fermi":12.6914,"total_energy":-55.350070605},{"ecutrho":380,"k_density":0.125,"ecutwfc":55,"n_iterations":11,"time":69162,"converged":true,"accuracy":5.3e-10,"fermi":12.7347,"total_energy":-55.350649595},{"ecutrho":100,"k_density":0.1,"ecutwfc":60,"n_iterations":13,"time":144113,"converged":true,"accuracy":5.1e-10,"fermi":12.7311,"total_energy":-55.35384649},{"ecutrho":100,"k_density":0.5,"ecutwfc":60,"n_iterations":21,"time":1094,"converged":true,"accuracy":4.0e-10,"fermi":12.5013,"total_energy":-55.34763912},{"ecutrho":100,"k_density":0.25,"ecutwfc":60,"n_iterations":13,"time":8111,"converged":true,"accuracy":6.0e-12,"fermi":12.8006,"total_energy":-55.35430223},{"ecutrho":100,"k_density":0.16666666666666666,"ecutwfc":60,"n_iterations":12,"time":27132,"converged":true,"accuracy":7.4e-10,"fermi":12.7113,"total_energy":-55.353342345},{"ecutrho":100,"k_density":0.125,"ecutwfc":60,"n_iterations":11,"time":65123,"converged":true,"accuracy":6.9e-10,"fermi":12.7546,"total_energy":-55.353920395},{"ecutrho":140,"k_density":0.1,"ecutwfc":60,"n_iterations":12,"time":139047,"converged":true,"accuracy":3.7e-10,"fermi":12.7119,"total_energy":-55.3508897},{"ecutrho":140,"k_density":0.5,"ecutwfc":60,"n_iterations":23,"time":2019,"converged":true,"accuracy":5.9e-12,"fermi":12.4814,"total_energy":-55.344599745},{"ecutrho":140,"k_density":0.25,"ecutwfc":60,"n_iterations":13,"time":8108,"converged":true,"accuracy":3.1e-11,"fermi":12.7816,"total_energy":-55.35136009},{"ecutrho":140,"k_density":0.16666666666666666,"ecutwfc":60,"n_iterations":12,"time":28146,"converged":true,"accuracy":6.6e-11,"fermi":12.6921,"total_energy":-55.350386505},{"ecutrho":140,"k_density":0.125,"ecutwfc":60,"n_iterations":11,"time":67095,"converged":true,"accuracy":2.9e-10,"fermi":12.7354,"total_energy":-55.35096279},{"ecutrho":180,"k_density":0.1,"ecutwfc":60,"n_iterations":12,"time":143054,"converged":true,"accuracy":4.2e-10,"fermi":12.711,"total_energy":-55.3506266},{"ecutrho":180,"k_density":0.5,"ecutwfc":60,"n_iterations":17,"time":1063,"converged":true,"accuracy":3.5e-11,"fermi":12.4806,"total_energy":-55.344336205},{"ecutrho":180,"k_density":0.25,"ecutwfc":60,"n_iterations":11,"time":7112,"converged":true,"accuracy":4.6e-10,"fermi":12.7808,"total_energy":-55.35109713},{"ecutrho":180,"k_density":0.16666666666666666,"ecutwfc":60,"n_iterations":12,"time":29164,"converged":true,"accuracy":2.6e-10,"fermi":12.6912,"total_energy":-55.350123395},{"ecutrho":180,"k_density":0.125,"ecutwfc":60,"n_iterations":11,"time":67094,"converged":true,"accuracy":3.2e-10,"fermi":12.7346,"total_energy":-55.350699745},{"ecutrho":220,"k_density":0.1,"ecutwfc":60,"n_iterations":12,"time":144146,"converged":true,"accuracy":4.0e-10,"fermi":12.7112,"total_energy":-55.35068126},{"ecutrho":220,"k_density":0.5,"ecutwfc":60,"n_iterations":18,"time":1075,"converged":true,"accuracy":2.1e-10,"fermi":12.4807,"total_energy":-55.34438974},{"ecutrho":220,"k_density":0.25,"ecutwfc":60,"n_iterations":11,"time":7126,"converged":true,"accuracy":5.7e-10,"fermi":12.7809,"total_energy":-55.35115208},{"ecutrho":220,"k_density":0.16666666666666666,"ecutwfc":60,"n_iterations":12,"time":29133,"converged":true,"accuracy":3.1e-11,"fermi":12.6914,"total_energy":-55.35017805},{"ecutrho":220,"k_density":0.125,"ecutwfc":60,"n_iterations":11,"time":68099,"converged":true,"accuracy":3.2e-10,"fermi":12.7347,"total_energy":-55.35075437},{"ecutrho":260,"k_density":0.1,"ecutwfc":60,"n_iterations":12,"time":154168,"converged":true,"accuracy":3.5e-10,"fermi":12.711,"total_energy":-55.35068013},{"ecutrho":260,"k_density":0.5,"ecutwfc":60,"n_iterations":17,"time":1075,"converged":true,"accuracy":4.1e-10,"fermi":12.4806,"total_energy":-55.344387365},{"ecutrho":260,"k_density":0.25,"ecutwfc":60,"n_iterations":11,"time":8090,"converged":true,"accuracy":6.4e-10,"fermi":12.7808,"total_energy":-55.351151355},{"ecutrho":260,"k_density":0.16666666666666666,"ecutwfc":60,"n_iterations":12,"time":32141,"converged":true,"accuracy":9.9e-10,"fermi":12.6913,"total_energy":-55.350176925},{"ecutrho":300,"k_density":0.1,"ecutwfc":60,"n_iterations":12,"time":155097,"converged":true,"accuracy":3.3e-10,"fermi":12.711,"total_energy":-55.350677855},{"ecutrho":300,"k_density":0.5,"ecutwfc":60,"n_iterations":17,"time":1081,"converged":true,"accuracy":9.6e-11,"fermi":12.4806,"total_energy":-55.34438481},{"ecutrho":300,"k_density":0.25,"ecutwfc":60,"n_iterations":13,"time":10057,"converged":true,"accuracy":3.2e-10,"fermi":12.7807,"total_energy":-55.351149165},{"ecutrho":300,"k_density":0.16666666666666666,"ecutwfc":60,"n_iterations":13,"time":34159,"converged":true,"accuracy":1.2e-10,"fermi":12.6912,"total_energy":-55.350174655},{"ecutrho":340,"k_density":0.1,"ecutwfc":60,"n_iterations":12,"time":154152,"converged":true,"accuracy":3.3e-10,"fermi":12.711,"total_energy":-55.35068375},{"ecutrho":340,"k_density":0.5,"ecutwfc":60,"n_iterations":17,"time":1083,"converged":true,"accuracy":9.8e-11,"fermi":12.4806,"total_energy":-55.34439064},{"ecutrho":340,"k_density":0.25,"ecutwfc":60,"n_iterations":13,"time":10049,"converged":true,"accuracy":3.1e-10,"fermi":12.7807,"total_energy":-55.3511551},{"ecutrho":340,"k_density":0.16666666666666666,"ecutwfc":60,"n_iterations":13,"time":35110,"converged":true,"accuracy":9.6e-11,"fermi":12.6912,"total_energy":-55.35018055},{"ecutrho":340,"k_density":0.125,"ecutwfc":60,"n_iterations":11,"time":74051,"converged":true,"accuracy":3.4e-10,"fermi":12.7345,"total_energy":-55.350756705},{"ecutrho":380,"k_density":0.1,"ecutwfc":60,"n_iterations":12,"time":154097,"converged":true,"accuracy":3.3e-10,"fermi":12.711,"total_energy":-55.35068203},{"ecutrho":380,"k_density":0.5,"ecutwfc":60,"n_iterations":17,"time":1081,"converged":true,"accuracy":2.8e-10,"fermi":12.4806,"total_energy":-55.34438905},{"ecutrho":380,"k_density":0.25,"ecutwfc":60,"n_iterations":13,"time":10056,"converged":true,"accuracy":3.2e-10,"fermi":12.7807,"total_energy":-55.351153315},{"ecutrho":380,"k_density":0.16666666666666666,"ecutwfc":60,"n_iterations":13,"time":35146,"converged":true,"accuracy":9.6e-11,"fermi":12.6912,"total_energy":-55.350178835},{"ecutrho":380,"k_density":0.125,"ecutwfc":60,"n_iterations":11,"time":74067,"converged":true,"accuracy":3.2e-10,"fermi":12.7345,"total_energy":-55.350755005},{"ecutrho":100,"k_density":0.1,"ecutwfc":65,"n_iterations":13,"time":147118,"converged":true,"accuracy":3.4e-10,"fermi":12.7309,"total_energy":-55.353942315},{"ecutrho":100,"k_density":0.5,"ecutwfc":65,"n_iterations":18,"time":1065,"converged":true,"accuracy":5.9e-10,"fermi":12.5011,"total_energy":-55.347721795},{"ecutrho":100,"k_density":0.25,"ecutwfc":65,"n_iterations":12,"time":8068,"converged":true,"accuracy":5.7e-11,"fermi":12.8004,"total_energy":-55.354401695},{"ecutrho":100,"k_density":0.16666666666666666,"ecutwfc":65,"n_iterations":12,"time":29130,"converged":true,"accuracy":4.8e-11,"fermi":12.7112,"total_energy":-55.35343647},{"ecutrho":100,"k_density":0.125,"ecutwfc":65,"n_iterations":12,"time":69175,"converged":true,"accuracy":4.8e-10,"fermi":12.7544,"total_energy":-55.354017155},{"ecutrho":140,"k_density":0.1,"ecutwfc":65,"n_iterations":12,"time":144139,"converged":true,"accuracy":9.5e-12,"fermi":12.7116,"total_energy":-55.35097094},{"ecutrho":140,"k_density":0.5,"ecutwfc":65,"n_iterations":19,"time":1069,"converged":true,"accuracy":3.2e-10,"fermi":12.4812,"total_energy":-55.344669515},{"ecutrho":140,"k_density":0.25,"ecutwfc":65,"n_iterations":14,"time":9095,"converged":true,"accuracy":3.5e-11,"fermi":12.7813,"total_energy":-55.351444505},{"ecutrho":140,"k_density":0.16666666666666666,"ecutwfc":65,"n_iterations":10,"time":24089,"converged":true,"accuracy":6.5e-10,"fermi":12.6919,"total_energy":-55.3504662},{"ecutrho":140,"k_density":0.125,"ecutwfc":65,"n_iterations":13,"time":74129,"converged":true,"accuracy":1.1e-10,"fermi":12.7352,"total_energy":-55.351044955},{"ecutrho":180,"k_density":0.1,"ecutwfc":65,"n_iterations":12,"time":144074,"converged":true,"accuracy":2.6e-11,"fermi":12.7107,"total_energy":-55.350708645},{"ecutrho":180,"k_density":0.5,"ecutwfc":65,"n_iterations":18,"time":1074,"converged":true,"accuracy":2.3e-10,"fermi":12.4803,"total_energy":-55.344406545},{"ecutrho":180,"k_density":0.25,"ecutwfc":65,"n_iterations":21,"time":13134,"converged":true,"accuracy":2.4e-10,"fermi":12.7804,"total_energy":-55.35118241},{"ecutrho":180,"k_density":0.16666666666666666,"ecutwfc":65,"n_iterations":10,"time":24101,"converged":true,"accuracy":9.5e-10,"fermi":12.6911,"total_energy":-55.350203885},{"ecutrho":180,"k_density":0.125,"ecutwfc":65,"n_iterations":13,"time":77128,"converged":true,"accuracy":8.5e-11,"fermi":12.7343,"total_energy":-55.35078271},{"ecutrho":220,"k_density":0.1,"ecutwfc":65,"n_iterations":12,"time":147146,"converged":true,"accuracy":1.2e-11,"fermi":12.7109,"total_energy":-55.350762905},{"ecutrho":220,"k_density":0.5,"ecutwfc":65,"n_iterations":18,"time":1064,"converged":true,"accuracy":9.4e-10,"fermi":12.4804,"total_energy":-55.344459825},{"ecutrho":220,"k_density":0.25,"ecutwfc":65,"n_iterations":14,"time":9111,"converged":true,"accuracy":1.9e-10,"fermi":12.7806,"total_energy":-55.351236945},{"ecutrho":220,"k_density":0.16666666666666666,"ecutwfc":65,"n_iterations":10,"time":24155,"converged":true,"accuracy":7.0e-10,"fermi":12.6912,"total_energy":-55.35025815},{"ecutrho":220,"k_density":0.125,"ecutwfc":65,"n_iterations":13,"time":76186,"converged":true,"accuracy":1.0e-10,"fermi":12.7344,"total_energy":-55.35083694},{"ecutrho":260,"k_density":0.1,"ecutwfc":65,"n_iterations":12,"time":162099,"converged":true,"accuracy":1.4e-11,"fermi":12.7107,"total_energy":-55.35076193},{"ecutrho":260,"k_density":0.5,"ecutwfc":65,"n_iterations":19,"time":1082,"converged":true,"accuracy":2.4e-10,"fermi":12.4803,"total_energy":-55.344457545},{"ecutrho":260,"k_density":0.25,"ecutwfc":65,"n_iterations":14,"time":10048,"converged":true,"accuracy":1.6e-10,"fermi":12.7804,"total_energy":-55.35123637},{"ecutrho":260,"k_density":0.16666666666666666,"ecutwfc":65,"n_iterations":13,"time":38100,"converged":true,"accuracy":4.1e-10,"fermi":12.691,"total_energy":-55.35025718},{"ecutrho":260,"k_density":0.125,"ecutwfc":65,"n_iterations":13,"time":86041,"converged":true,"accuracy":7.9e-11,"fermi":12.7343,"total_energy":-55.350835855},{"ecutrho":300,"k_density":0.1,"ecutwfc":65,"n_iterations":12,"time":162083,"converged":true,"accuracy":2.4e-11,"fermi":12.7107,"total_energy":-55.350759745},{"ecutrho":300,"k_density":0.5,"ecutwfc":65,"n_iterations":18,"time":1078,"converged":true,"accuracy":1.0e-9,"fermi":12.4803,"total_energy":-55.34445504},{"ecutrho":300,"k_density":0.25,"ecutwfc":65,"n_iterations":21,"time":14111,"converged":true,"accuracy":7.8e-11,"fermi":12.7804,"total_energy":-55.351234275},{"ecutrho":300,"k_density":0.16666666666666666,"ecutwfc":65,"n_iterations":10,"time":27097,"converged":true,"accuracy":8.7e-10,"fermi":12.691,"total_energy":-55.350254995},{"ecutrho":300,"k_density":0.125,"ecutwfc":65,"n_iterations":13,"time":85073,"converged":true,"accuracy":8.5e-11,"fermi":12.7342,"total_energy":-55.35083363},{"ecutrho":340,"k_density":0.1,"ecutwfc":65,"n_iterations":12,"time":162049,"converged":true,"accuracy":2.2e-11,"fermi":12.7107,"total_energy":-55.350765625},{"ecutrho":340,"k_density":0.5,"ecutwfc":65,"n_iterations":19,"time":1089,"converged":true,"accuracy":2.2e-10,"fermi":12.4803,"total_energy":-55.34446086},{"ecutrho":340,"k_density":0.25,"ecutwfc":65,"n_iterations":16,"time":11109,"converged":true,"accuracy":1.2e-10,"fermi":12.7804,"total_energy":-55.35124019},{"ecutrho":340,"k_density":0.16666666666666666,"ecutwfc":65,"n_iterations":10,"time":28012,"converged":true,"accuracy":9.7e-10,"fermi":12.691,"total_energy":-55.350260875},{"ecutrho":340,"k_density":0.125,"ecutwfc":65,"n_iterations":13,"time":86110,"converged":true,"accuracy":8.5e-11,"fermi":12.7342,"total_energy":-55.350839505},{"ecutrho":380,"k_density":0.1,"ecutwfc":65,"n_iterations":12,"time":162082,"converged":true,"accuracy":1.9e-11,"fermi":12.7107,"total_energy":-55.35076388},{"ecutrho":380,"k_density":0.5,"ecutwfc":65,"n_iterations":19,"time":1093,"converged":true,"accuracy":2.2e-10,"fermi":12.4803,"total_energy":-55.344459255},{"ecutrho":380,"k_density":0.25,"ecutwfc":65,"n_iterations":14,"time":10057,"converged":true,"accuracy":4.9e-10,"fermi":12.7804,"total_energy":-55.35123838},{"ecutrho":380,"k_density":0.16666666666666666,"ecutwfc":65,"n_iterations":10,"time":28012,"converged":true,"accuracy":1.0e-9,"fermi":12.691,"total_energy":-55.35025913},{"ecutrho":380,"k_density":0.125,"ecutwfc":65,"n_iterations":13,"time":86054,"converged":true,"accuracy":7.4e-11,"fermi":12.7342,"total_energy":-55.350837775},{"ecutrho":100,"k_density":0.1,"ecutwfc":70,"n_iterations":13,"time":149108,"converged":true,"accuracy":4.1e-10,"fermi":12.7309,"total_energy":-55.353999285},{"ecutrho":100,"k_density":0.5,"ecutwfc":70,"n_iterations":20,"time":1083,"converged":true,"accuracy":4.5e-10,"fermi":12.501,"total_energy":-55.347783695},{"ecutrho":100,"k_density":0.25,"ecutwfc":70,"n_iterations":13,"time":8133,"converged":true,"accuracy":4.4e-10,"fermi":12.8003,"total_energy":-55.35445795},{"ecutrho":100,"k_density":0.16666666666666666,"ecutwfc":70,"n_iterations":13,"time":31123,"converged":true,"accuracy":1.0e-9,"fermi":12.7111,"total_energy":-55.353493955},{"ecutrho":100,"k_density":0.125,"ecutwfc":70,"n_iterations":13,"time":74099,"converged":true,"accuracy":3.2e-10,"fermi":12.7544,"total_energy":-55.35407395},{"ecutrho":140,"k_density":0.1,"ecutwfc":70,"n_iterations":12,"time":145107,"converged":true,"accuracy":6.1e-12,"fermi":12.7115,"total_energy":-55.35101354},{"ecutrho":140,"k_density":0.5,"ecutwfc":70,"n_iterations":20,"time":1088,"converged":true,"accuracy":3.2e-10,"fermi":12.481,"total_energy":-55.344715755},{"ecutrho":140,"k_density":0.25,"ecutwfc":70,"n_iterations":21,"time":12074,"converged":true,"accuracy":4.1e-10,"fermi":12.7811,"total_energy":-55.351486345},{"ecutrho":140,"k_density":0.16666666666666666,"ecutwfc":70,"n_iterations":10,"time":24102,"converged":true,"accuracy":5.0e-10,"fermi":12.6917,"total_energy":-55.35050925},{"ecutrho":140,"k_density":0.125,"ecutwfc":70,"n_iterations":13,"time":75123,"converged":true,"accuracy":2.1e-10,"fermi":12.735,"total_energy":-55.351087495},{"ecutrho":180,"k_density":0.1,"ecutwfc":70,"n_iterations":12,"time":146104,"converged":true,"accuracy":1.1e-11,"fermi":12.7106,"total_energy":-55.350752295},{"ecutrho":180,"k_density":0.5,"ecutwfc":70,"n_iterations":21,"time":1088,"converged":true,"accuracy":9.4e-10,"fermi":12.4802,"total_energy":-55.344454015},{"ecutrho":180,"k_density":0.25,"ecutwfc":70,"n_iterations":16,"time":10078,"converged":true,"accuracy":1.4e-10,"fermi":12.7803,"total_energy":-55.351225305},{"ecutrho":180,"k_density":0.16666666666666666,"ecutwfc":70,"n_iterations":10,"time":24102,"converged":true,"accuracy":6.4e-10,"fermi":12.6908,"total_energy":-55.35024799},{"ecutrho":220,"k_density":0.1,"ecutwfc":70,"n_iterations":12,"time":148103,"converged":true,"accuracy":8.3e-12,"fermi":12.7107,"total_energy":-55.350806235},{"ecutrho":220,"k_density":0.5,"ecutwfc":70,"n_iterations":21,"time":1098,"converged":true,"accuracy":2.9e-11,"fermi":12.4803,"total_energy":-55.34450687},{"ecutrho":220,"k_density":0.25,"ecutwfc":70,"n_iterations":23,"time":14057,"converged":true,"accuracy":6.9e-11,"fermi":12.7804,"total_energy":-55.35127953},{"ecutrho":220,"k_density":0.16666666666666666,"ecutwfc":70,"n_iterations":10,"time":24171,"converged":true,"accuracy":4.7e-10,"fermi":12.691,"total_energy":-55.35030193},{"ecutrho":220,"k_density":0.125,"ecutwfc":70,"n_iterations":13,"time":77138,"converged":true,"accuracy":1.6e-10,"fermi":12.7343,"total_energy":-55.350880195},{"ecutrho":260,"k_density":0.1,"ecutwfc":70,"n_iterations":12,"time":163103,"converged":true,"accuracy":1.1e-11,"fermi":12.7106,"total_energy":-55.350805315},{"ecutrho":260,"k_density":0.5,"ecutwfc":70,"n_iterations":21,"time":1102,"converged":true,"accuracy":2.6e-12,"fermi":12.4802,"total_energy":-55.34450467},{"ecutrho":260,"k_density":0.25,"ecutwfc":70,"n_iterations":23,"time":15080,"converged":true,"accuracy":2.6e-10,"fermi":12.7803,"total_energy":-55.351279},{"ecutrho":260,"k_density":0.16666666666666666,"ecutwfc":70,"n_iterations":10,"time":28026,"converged":true,"accuracy":8.6e-10,"fermi":12.6908,"total_energy":-55.350301015},{"ecutrho":260,"k_density":0.125,"ecutwfc":70,"n_iterations":13,"time":86086,"converged":true,"accuracy":1.7e-10,"fermi":12.7341,"total_energy":-55.35087917},{"ecutrho":300,"k_density":0.1,"ecutwfc":70,"n_iterations":12,"time":163040,"converged":true,"accuracy":1.1e-11,"fermi":12.7106,"total_energy":-55.350803215},{"ecutrho":300,"k_density":0.5,"ecutwfc":70,"n_iterations":21,"time":1115,"converged":true,"accuracy":3.5e-11,"fermi":12.4801,"total_energy":-55.34450226},{"ecutrho":300,"k_density":0.25,"ecutwfc":70,"n_iterations":23,"time":15104,"converged":true,"accuracy":3.1e-11,"fermi":12.7803,"total_energy":-55.35127699},{"ecutrho":300,"k_density":0.16666666666666666,"ecutwfc":70,"n_iterations":10,"time":28035,"converged":true,"accuracy":6.6e-10,"fermi":12.6908,"total_energy":-55.35029892},{"ecutrho":340,"k_density":0.1,"ecutwfc":70,"n_iterations":12,"time":164021,"converged":true,"accuracy":1.3e-11,"fermi":12.7106,"total_energy":-55.350809085},{"ecutrho":340,"k_density":0.5,"ecutwfc":70,"n_iterations":21,"time":1110,"converged":true,"accuracy":2.8e-11,"fermi":12.4801,"total_energy":-55.344508065},{"ecutrho":340,"k_density":0.25,"ecutwfc":70,"n_iterations":23,"time":15079,"converged":true,"accuracy":1.9e-10,"fermi":12.7803,"total_energy":-55.351282895},{"ecutrho":340,"k_density":0.16666666666666666,"ecutwfc":70,"n_iterations":10,"time":28067,"converged":true,"accuracy":5.4e-10,"fermi":12.6908,"total_energy":-55.35030479},{"ecutrho":340,"k_density":0.125,"ecutwfc":70,"n_iterations":13,"time":87032,"converged":true,"accuracy":1.6e-10,"fermi":12.7341,"total_energy":-55.35088289},{"ecutrho":380,"k_density":0.1,"ecutwfc":70,"n_iterations":12,"time":163039,"converged":true,"accuracy":1.4e-11,"fermi":12.7106,"total_energy":-55.35080731},{"ecutrho":380,"k_density":0.5,"ecutwfc":70,"n_iterations":21,"time":1112,"converged":true,"accuracy":9.4e-12,"fermi":12.4802,"total_energy":-55.34450643},{"ecutrho":380,"k_density":0.25,"ecutwfc":70,"n_iterations":23,"time":15080,"converged":true,"accuracy":4.3e-12,"fermi":12.7803,"total_energy":-55.35128106},{"ecutrho":380,"k_density":0.16666666666666666,"ecutwfc":70,"n_iterations":10,"time":28090,"converged":true,"accuracy":6.5e-10,"fermi":12.6908,"total_energy":-55.350303015},{"ecutrho":100,"k_density":0.5,"ecutwfc":75,"n_iterations":20,"time":1080,"converged":true,"accuracy":7.3e-10,"fermi":12.5011,"total_energy":-55.347812365},{"ecutrho":140,"k_density":0.1,"ecutwfc":75,"n_iterations":12,"time":148143,"converged":true,"accuracy":1.8e-11,"fermi":12.7114,"total_energy":-55.3510324},{"ecutrho":140,"k_density":0.5,"ecutwfc":75,"n_iterations":19,"time":1074,"converged":true,"accuracy":9.8e-10,"fermi":12.4809,"total_energy":-55.344734545},{"ecutrho":140,"k_density":0.25,"ecutwfc":75,"n_iterations":14,"time":9131,"converged":true,"accuracy":1.8e-10,"fermi":12.7811,"total_energy":-55.35150493},{"ecutrho":140,"k_density":0.16666666666666666,"ecutwfc":75,"n_iterations":12,"time":31139,"converged":true,"accuracy":4.4e-10,"fermi":12.6917,"total_energy":-55.35052806},{"ecutrho":140,"k_density":0.125,"ecutwfc":75,"n_iterations":13,"time":76136,"converged":true,"accuracy":2.1e-10,"fermi":12.7349,"total_energy":-55.351106555},{"ecutrho":180,"k_density":0.1,"ecutwfc":75,"n_iterations":12,"time":148072,"converged":true,"accuracy":6.1e-11,"fermi":12.7105,"total_energy":-55.350771845},{"ecutrho":180,"k_density":0.5,"ecutwfc":75,"n_iterations":21,"time":1091,"converged":true,"accuracy":6.0e-10,"fermi":12.4801,"total_energy":-55.34447346},{"ecutrho":180,"k_density":0.25,"ecutwfc":75,"n_iterations":15,"time":10078,"converged":true,"accuracy":5.1e-10,"fermi":12.7802,"total_energy":-55.351244615},{"ecutrho":180,"k_density":0.16666666666666666,"ecutwfc":75,"n_iterations":12,"time":31157,"converged":true,"accuracy":4.8e-10,"fermi":12.6908,"total_energy":-55.350267495},{"ecutrho":180,"k_density":0.125,"ecutwfc":75,"n_iterations":13,"time":77093,"converged":true,"accuracy":3.7e-10,"fermi":12.7341,"total_energy":-55.350846045},{"ecutrho":220,"k_density":0.1,"ecutwfc":75,"n_iterations":12,"time":152091,"converged":true,"accuracy":3.2e-11,"fermi":12.7107,"total_energy":-55.350825655},{"ecutrho":220,"k_density":0.5,"ecutwfc":75,"n_iterations":19,"time":1082,"converged":true,"accuracy":4.5e-11,"fermi":12.4802,"total_energy":-55.34452621},{"ecutrho":220,"k_density":0.25,"ecutwfc":75,"n_iterations":14,"time":9128,"converged":true,"accuracy":3.4e-10,"fermi":12.7804,"total_energy":-55.3512987},{"ecutrho":220,"k_density":0.16666666666666666,"ecutwfc":75,"n_iterations":12,"time":32123,"converged":true,"accuracy":4.7e-10,"fermi":12.6909,"total_energy":-55.350321305},{"ecutrho":260,"k_density":0.1,"ecutwfc":75,"n_iterations":12,"time":167042,"converged":true,"accuracy":3.1e-11,"fermi":12.7105,"total_energy":-55.350824685},{"ecutrho":260,"k_density":0.5,"ecutwfc":75,"n_iterations":19,"time":1098,"converged":true,"accuracy":5.3e-10,"fermi":12.4801,"total_energy":-55.34452396},{"ecutrho":260,"k_density":0.25,"ecutwfc":75,"n_iterations":15,"time":11105,"converged":true,"accuracy":5.6e-11,"fermi":12.7802,"total_energy":-55.35129812},{"ecutrho":260,"k_density":0.16666666666666666,"ecutwfc":75,"n_iterations":12,"time":35117,"converged":true,"accuracy":4.4e-10,"fermi":12.6908,"total_energy":-55.350320345},{"ecutrho":260,"k_density":0.125,"ecutwfc":75,"n_iterations":13,"time":86072,"converged":true,"accuracy":3.1e-10,"fermi":12.7341,"total_energy":-55.35089875},{"ecutrho":300,"k_density":0.1,"ecutwfc":75,"n_iterations":12,"time":179143,"converged":true,"accuracy":4.0e-11,"fermi":12.7105,"total_energy":-55.350822635},{"ecutrho":300,"k_density":0.5,"ecutwfc":75,"n_iterations":18,"time":1100,"converged":true,"accuracy":8.0e-11,"fermi":12.4801,"total_energy":-55.344521595},{"ecutrho":300,"k_density":0.25,"ecutwfc":75,"n_iterations":15,"time":12097,"converged":true,"accuracy":1.5e-10,"fermi":12.7802,"total_energy":-55.35129616},{"ecutrho":300,"k_density":0.16666666666666666,"ecutwfc":75,"n_iterations":12,"time":38108,"converged":true,"accuracy":5.0e-10,"fermi":12.6908,"total_energy":-55.350318295},{"ecutrho":300,"k_density":0.125,"ecutwfc":75,"n_iterations":13,"time":94059,"converged":true,"accuracy":3.0e-10,"fermi":12.734,"total_energy":-55.35089666},{"ecutrho":340,"k_density":0.5,"ecutwfc":75,"n_iterations":18,"time":1111,"converged":true,"accuracy":8.7e-11,"fermi":12.4801,"total_energy":-55.34452739},{"ecutrho":340,"k_density":0.25,"ecutwfc":75,"n_iterations":15,"time":12116,"converged":true,"accuracy":5.0e-10,"fermi":12.7802,"total_energy":-55.35130205},{"ecutrho":340,"k_density":0.125,"ecutwfc":75,"n_iterations":13,"time":94049,"converged":true,"accuracy":3.0e-10,"fermi":12.734,"total_energy":-55.350902505},{"ecutrho":380,"k_density":0.1,"ecutwfc":75,"n_iterations":12,"time":180110,"converged":true,"accuracy":4.1e-11,"fermi":12.7105,"total_energy":-55.350826705},{"ecutrho":380,"k_density":0.5,"ecutwfc":75,"n_iterations":18,"time":1108,"converged":true,"accuracy":1.6e-10,"fermi":12.4801,"total_energy":-55.34452574},{"ecutrho":380,"k_density":0.25,"ecutwfc":75,"n_iterations":15,"time":12089,"converged":true,"accuracy":1.4e-10,"fermi":12.7802,"total_energy":-55.3513002},{"ecutrho":380,"k_density":0.16666666666666666,"ecutwfc":75,"n_iterations":12,"time":39060,"converged":true,"accuracy":5.0e-10,"fermi":12.6908,"total_energy":-55.350322365},{"ecutrho":380,"k_density":0.125,"ecutwfc":75,"n_iterations":13,"time":93079,"converged":true,"accuracy":3.7e-10,"fermi":12.734,"total_energy":-55.350900735},{"ecutrho":100,"k_density":0.5,"ecutwfc":80,"n_iterations":21,"time":1093,"converged":true,"accuracy":6.0e-10,"fermi":12.5011,"total_energy":-55.34782654},{"ecutrho":140,"k_density":0.1,"ecutwfc":80,"n_iterations":12,"time":148118,"converged":true,"accuracy":1.0e-11,"fermi":12.7114,"total_energy":-55.351044955},{"ecutrho":140,"k_density":0.5,"ecutwfc":80,"n_iterations":18,"time":1076,"converged":true,"accuracy":1.4e-10,"fermi":12.4809,"total_energy":-55.34474605},{"ecutrho":140,"k_density":0.25,"ecutwfc":80,"n_iterations":15,"time":10101,"converged":true,"accuracy":7.9e-10,"fermi":12.7811,"total_energy":-55.351516915},{"ecutrho":140,"k_density":0.16666666666666666,"ecutwfc":80,"n_iterations":12,"time":29149,"converged":true,"accuracy":4.4e-10,"fermi":12.6917,"total_energy":-55.350540475},{"ecutrho":140,"k_density":0.125,"ecutwfc":80,"n_iterations":12,"time":74128,"converged":true,"accuracy":1.8e-10,"fermi":12.7349,"total_energy":-55.35111902},{"ecutrho":180,"k_density":0.1,"ecutwfc":80,"n_iterations":12,"time":149099,"converged":true,"accuracy":4.7e-11,"fermi":12.7105,"total_energy":-55.350784695},{"ecutrho":180,"k_density":0.5,"ecutwfc":80,"n_iterations":21,"time":1090,"converged":true,"accuracy":7.4e-10,"fermi":12.4801,"total_energy":-55.344485195},{"ecutrho":180,"k_density":0.25,"ecutwfc":80,"n_iterations":15,"time":10088,"converged":true,"accuracy":3.6e-10,"fermi":12.7803,"total_energy":-55.351256875},{"ecutrho":180,"k_density":0.16666666666666666,"ecutwfc":80,"n_iterations":12,"time":29161,"converged":true,"accuracy":1.1e-10,"fermi":12.6908,"total_energy":-55.350280195},{"ecutrho":180,"k_density":0.125,"ecutwfc":80,"n_iterations":12,"time":74144,"converged":true,"accuracy":5.7e-10,"fermi":12.734,"total_energy":-55.350858805},{"ecutrho":220,"k_density":0.1,"ecutwfc":80,"n_iterations":12,"time":152121,"converged":true,"accuracy":3.0e-11,"fermi":12.7106,"total_energy":-55.350838425},{"ecutrho":220,"k_density":0.5,"ecutwfc":80,"n_iterations":17,"time":1073,"converged":true,"accuracy":1.5e-10,"fermi":12.4802,"total_energy":-55.344537905},{"ecutrho":220,"k_density":0.25,"ecutwfc":80,"n_iterations":14,"time":10040,"converged":true,"accuracy":2.6e-10,"fermi":12.7804,"total_energy":-55.351310895},{"ecutrho":220,"k_density":0.16666666666666666,"ecutwfc":80,"n_iterations":12,"time":30126,"converged":true,"accuracy":8.0e-11,"fermi":12.6909,"total_energy":-55.35033393},{"ecutrho":220,"k_density":0.125,"ecutwfc":80,"n_iterations":12,"time":77042,"converged":true,"accuracy":2.7e-10,"fermi":12.7342,"total_energy":-55.3509125},{"ecutrho":260,"k_density":0.1,"ecutwfc":80,"n_iterations":12,"time":167060,"converged":true,"accuracy":3.6e-11,"fermi":12.7105,"total_energy":-55.350837385},{"ecutrho":260,"k_density":0.5,"ecutwfc":80,"n_iterations":21,"time":1108,"converged":true,"accuracy":5.4e-10,"fermi":12.4801,"total_energy":-55.344535585},{"ecutrho":260,"k_density":0.25,"ecutwfc":80,"n_iterations":18,"time":14039,"converged":true,"accuracy":7.0e-11,"fermi":12.7802,"total_energy":-55.351310245},{"ecutrho":260,"k_density":0.16666666666666666,"ecutwfc":80,"n_iterations":12,"time":34059,"converged":true,"accuracy":1.1e-10,"fermi":12.6908,"total_energy":-55.350332895},{"ecutrho":260,"k_density":0.125,"ecutwfc":80,"n_iterations":12,"time":84039,"converged":true,"accuracy":2.8e-10,"fermi":12.734,"total_energy":-55.35091136},{"ecutrho":300,"k_density":0.1,"ecutwfc":80,"n_iterations":12,"time":180172,"converged":true,"accuracy":4.8e-11,"fermi":12.7105,"total_energy":-55.35083534},{"ecutrho":300,"k_density":0.5,"ecutwfc":80,"n_iterations":21,"time":2030,"converged":true,"accuracy":4.4e-10,"fermi":12.4801,"total_energy":-55.344533225},{"ecutrho":300,"k_density":0.25,"ecutwfc":80,"n_iterations":17,"time":14086,"converged":true,"accuracy":6.4e-10,"fermi":12.7802,"total_energy":-55.35130829},{"ecutrho":300,"k_density":0.16666666666666666,"ecutwfc":80,"n_iterations":12,"time":37014,"converged":true,"accuracy":1.8e-10,"fermi":12.6907,"total_energy":-55.350330855},{"ecutrho":300,"k_density":0.125,"ecutwfc":80,"n_iterations":12,"time":90106,"converged":true,"accuracy":2.6e-10,"fermi":12.734,"total_energy":-55.35090928},{"ecutrho":340,"k_density":0.1,"ecutwfc":80,"n_iterations":12,"time":179161,"converged":true,"accuracy":4.8e-11,"fermi":12.7105,"total_energy":-55.350841185},{"ecutrho":340,"k_density":0.5,"ecutwfc":80,"n_iterations":21,"time":2033,"converged":true,"accuracy":2.8e-10,"fermi":12.4801,"total_energy":-55.344539005},{"ecutrho":340,"k_density":0.25,"ecutwfc":80,"n_iterations":17,"time":14091,"converged":true,"accuracy":9.6e-10,"fermi":12.7802,"total_energy":-55.35131417},{"ecutrho":340,"k_density":0.16666666666666666,"ecutwfc":80,"n_iterations":12,"time":37026,"converged":true,"accuracy":1.2e-10,"fermi":12.6907,"total_energy":-55.350336695},{"ecutrho":340,"k_density":0.125,"ecutwfc":80,"n_iterations":12,"time":90103,"converged":true,"accuracy":2.6e-10,"fermi":12.734,"total_energy":-55.35091511},{"ecutrho":380,"k_density":0.1,"ecutwfc":80,"n_iterations":12,"time":180138,"converged":true,"accuracy":4.6e-11,"fermi":12.7105,"total_energy":-55.350839395},{"ecutrho":380,"k_density":0.5,"ecutwfc":80,"n_iterations":21,"time":2039,"converged":true,"accuracy":8.6e-10,"fermi":12.4801,"total_energy":-55.344537355},{"ecutrho":380,"k_density":0.25,"ecutwfc":80,"n_iterations":18,"time":14140,"converged":true,"accuracy":4.7e-10,"fermi":12.7802,"total_energy":-55.351312315},{"ecutrho":380,"k_density":0.16666666666666666,"ecutwfc":80,"n_iterations":12,"time":37043,"converged":true,"accuracy":1.2e-10,"fermi":12.6907,"total_energy":-55.350334905},{"ecutrho":380,"k_density":0.125,"ecutwfc":80,"n_iterations":12,"time":90129,"converged":true,"accuracy":3.0e-10,"fermi":12.734,"total_energy":-55.35091334},{"ecutrho":140,"k_density":0.1,"ecutwfc":85,"n_iterations":11,"time":138131,"converged":true,"accuracy":7.2e-10,"fermi":12.7114,"total_energy":-55.35106226},{"ecutrho":140,"k_density":0.5,"ecutwfc":85,"n_iterations":19,"time":1076,"converged":true,"accuracy":9.4e-10,"fermi":12.4809,"total_energy":-55.34476438},{"ecutrho":140,"k_density":0.25,"ecutwfc":85,"n_iterations":14,"time":9107,"converged":true,"accuracy":2.3e-10,"fermi":12.7811,"total_energy":-55.351534815},{"ecutrho":140,"k_density":0.16666666666666666,"ecutwfc":85,"n_iterations":12,"time":32122,"converged":true,"accuracy":4.4e-10,"fermi":12.6916,"total_energy":-55.350557915},{"ecutrho":140,"k_density":0.125,"ecutwfc":85,"n_iterations":12,"time":74100,"converged":true,"accuracy":8.8e-10,"fermi":12.7349,"total_energy":-55.35113637},{"ecutrho":180,"k_density":0.1,"ecutwfc":85,"n_iterations":12,"time":151153,"converged":true,"accuracy":1.3e-11,"fermi":12.7105,"total_energy":-55.350802015},{"ecutrho":180,"k_density":0.5,"ecutwfc":85,"n_iterations":17,"time":1067,"converged":true,"accuracy":2.1e-10,"fermi":12.4801,"total_energy":-55.344503515},{"ecutrho":180,"k_density":0.25,"ecutwfc":85,"n_iterations":13,"time":8137,"converged":true,"accuracy":7.6e-10,"fermi":12.7802,"total_energy":-55.35127478},{"ecutrho":180,"k_density":0.16666666666666666,"ecutwfc":85,"n_iterations":12,"time":32102,"converged":true,"accuracy":4.2e-11,"fermi":12.6907,"total_energy":-55.35029766},{"ecutrho":180,"k_density":0.125,"ecutwfc":85,"n_iterations":13,"time":81019,"converged":true,"accuracy":8.7e-11,"fermi":12.734,"total_energy":-55.35087618},{"ecutrho":220,"k_density":0.1,"ecutwfc":85,"n_iterations":12,"time":154125,"converged":true,"accuracy":1.0e-11,"fermi":12.7106,"total_energy":-55.35085566},{"ecutrho":220,"k_density":0.5,"ecutwfc":85,"n_iterations":20,"time":1094,"converged":true,"accuracy":2.6e-10,"fermi":12.4802,"total_energy":-55.344556155},{"ecutrho":220,"k_density":0.25,"ecutwfc":85,"n_iterations":13,"time":9063,"converged":true,"accuracy":1.9e-10,"fermi":12.7803,"total_energy":-55.351328715},{"ecutrho":220,"k_density":0.16666666666666666,"ecutwfc":85,"n_iterations":12,"time":33092,"converged":true,"accuracy":1.6e-11,"fermi":12.6908,"total_energy":-55.350351305},{"ecutrho":220,"k_density":0.125,"ecutwfc":85,"n_iterations":13,"time":82047,"converged":true,"accuracy":9.8e-11,"fermi":12.7341,"total_energy":-55.35092979},{"ecutrho":260,"k_density":0.1,"ecutwfc":85,"n_iterations":12,"time":170067,"converged":true,"accuracy":9.7e-12,"fermi":12.7105,"total_energy":-55.350854565},{"ecutrho":260,"k_density":0.5,"ecutwfc":85,"n_iterations":19,"time":1098,"converged":true,"accuracy":7.6e-11,"fermi":12.48,"total_energy":-55.34455378},{"ecutrho":260,"k_density":0.25,"ecutwfc":85,"n_iterations":13,"time":10041,"converged":true,"accuracy":1.9e-10,"fermi":12.7802,"total_energy":-55.351328005},{"ecutrho":260,"k_density":0.16666666666666666,"ecutwfc":85,"n_iterations":12,"time":36112,"converged":true,"accuracy":1.7e-11,"fermi":12.6907,"total_energy":-55.350350215},{"ecutrho":260,"k_density":0.125,"ecutwfc":85,"n_iterations":13,"time":89053,"converged":true,"accuracy":9.1e-11,"fermi":12.734,"total_energy":-55.35092859},{"ecutrho":300,"k_density":0.1,"ecutwfc":85,"n_iterations":12,"time":183128,"converged":true,"accuracy":1.0e-11,"fermi":12.7104,"total_energy":-55.35085251},{"ecutrho":300,"k_density":0.5,"ecutwfc":85,"n_iterations":18,"time":1108,"converged":true,"accuracy":2.4e-11,"fermi":12.48,"total_energy":-55.344551405},{"ecutrho":300,"k_density":0.25,"ecutwfc":85,"n_iterations":13,"time":10133,"converged":true,"accuracy":2.2e-10,"fermi":12.7802,"total_energy":-55.351326035},{"ecutrho":300,"k_density":0.16666666666666666,"ecutwfc":85,"n_iterations":12,"time":39107,"converged":true,"accuracy":4.0e-11,"fermi":12.6907,"total_energy":-55.35034816},{"ecutrho":300,"k_density":0.125,"ecutwfc":85,"n_iterations":13,"time":96123,"converged":true,"accuracy":8.6e-11,"fermi":12.734,"total_energy":-55.3509265},{"ecutrho":340,"k_density":0.1,"ecutwfc":85,"n_iterations":12,"time":183117,"converged":true,"accuracy":9.9e-12,"fermi":12.7104,"total_energy":-55.35085833},{"ecutrho":340,"k_density":0.5,"ecutwfc":85,"n_iterations":18,"time":1118,"converged":true,"accuracy":2.3e-11,"fermi":12.48,"total_energy":-55.344557165},{"ecutrho":340,"k_density":0.25,"ecutwfc":85,"n_iterations":13,"time":10134,"converged":true,"accuracy":2.2e-10,"fermi":12.7802,"total_energy":-55.351331895},{"ecutrho":340,"k_density":0.16666666666666666,"ecutwfc":85,"n_iterations":12,"time":40096,"converged":true,"accuracy":6.7e-11,"fermi":12.6907,"total_energy":-55.350353985},{"ecutrho":340,"k_density":0.125,"ecutwfc":85,"n_iterations":13,"time":96142,"converged":true,"accuracy":8.7e-11,"fermi":12.734,"total_energy":-55.35093231},{"ecutrho":380,"k_density":0.1,"ecutwfc":85,"n_iterations":12,"time":184124,"converged":true,"accuracy":9.8e-12,"fermi":12.7104,"total_energy":-55.35085655},{"ecutrho":380,"k_density":0.5,"ecutwfc":85,"n_iterations":18,"time":2020,"converged":true,"accuracy":2.6e-10,"fermi":12.48,"total_energy":-55.34455552},{"ecutrho":380,"k_density":0.25,"ecutwfc":85,"n_iterations":13,"time":11090,"converged":true,"accuracy":2.1e-10,"fermi":12.7802,"total_energy":-55.35133005},{"ecutrho":380,"k_density":0.16666666666666666,"ecutwfc":85,"n_iterations":12,"time":40061,"converged":true,"accuracy":5.3e-11,"fermi":12.6907,"total_energy":-55.3503522},{"ecutrho":380,"k_density":0.125,"ecutwfc":85,"n_iterations":13,"time":97087,"converged":true,"accuracy":8.6e-11,"fermi":12.734,"total_energy":-55.350930545},{"ecutrho":140,"k_density":0.1,"ecutwfc":90,"n_iterations":12,"time":150093,"converged":true,"accuracy":1.1e-10,"fermi":12.7113,"total_energy":-55.351080645},{"ecutrho":140,"k_density":0.5,"ecutwfc":90,"n_iterations":17,"time":1074,"converged":true,"accuracy":2.4e-11,"fermi":12.4808,"total_energy":-55.34478299},{"ecutrho":140,"k_density":0.25,"ecutwfc":90,"n_iterations":17,"time":12047,"converged":true,"accuracy":2.1e-10,"fermi":12.781,"total_energy":-55.351552925},{"ecutrho":140,"k_density":0.16666666666666666,"ecutwfc":90,"n_iterations":12,"time":31179,"converged":true,"accuracy":6.1e-11,"fermi":12.6916,"total_energy":-55.35057633},{"ecutrho":140,"k_density":0.125,"ecutwfc":90,"n_iterations":13,"time":80001,"converged":true,"accuracy":6.2e-11,"fermi":12.7348,"total_energy":-55.35115468},{"ecutrho":180,"k_density":0.1,"ecutwfc":90,"n_iterations":12,"time":151151,"converged":true,"accuracy":1.6e-10,"fermi":12.7104,"total_energy":-55.35082031},{"ecutrho":180,"k_density":0.5,"ecutwfc":90,"n_iterations":23,"time":2027,"converged":true,"accuracy":9.9e-10,"fermi":12.48,"total_energy":-55.344522065},{"ecutrho":180,"k_density":0.25,"ecutwfc":90,"n_iterations":18,"time":13051,"converged":true,"accuracy":5.1e-11,"fermi":12.7802,"total_energy":-55.3512928},{"ecutrho":180,"k_density":0.16666666666666666,"ecutwfc":90,"n_iterations":12,"time":33127,"converged":true,"accuracy":3.5e-10,"fermi":12.6907,"total_energy":-55.35031598},{"ecutrho":180,"k_density":0.125,"ecutwfc":90,"n_iterations":13,"time":79060,"converged":true,"accuracy":1.0e-10,"fermi":12.734,"total_energy":-55.3508944},{"ecutrho":220,"k_density":0.5,"ecutwfc":90,"n_iterations":19,"time":1116,"converged":true,"accuracy":2.3e-10,"fermi":12.4801,"total_energy":-55.344574635},{"ecutrho":220,"k_density":0.25,"ecutwfc":90,"n_iterations":17,"time":11129,"converged":true,"accuracy":3.1e-12,"fermi":12.7803,"total_energy":-55.351346705},{"ecutrho":220,"k_density":0.16666666666666666,"ecutwfc":90,"n_iterations":12,"time":34166,"converged":true,"accuracy":2.5e-10,"fermi":12.6908,"total_energy":-55.350369595},{"ecutrho":220,"k_density":0.125,"ecutwfc":90,"n_iterations":13,"time":81075,"converged":true,"accuracy":8.1e-11,"fermi":12.7341,"total_energy":-55.350947975},{"ecutrho":260,"k_density":0.1,"ecutwfc":90,"n_iterations":12,"time":168112,"converged":true,"accuracy":1.3e-10,"fermi":12.7104,"total_energy":-55.35087277},{"ecutrho":260,"k_density":0.5,"ecutwfc":90,"n_iterations":21,"time":2028,"converged":true,"accuracy":9.1e-10,"fermi":12.48,"total_energy":-55.344572205},{"ecutrho":260,"k_density":0.25,"ecutwfc":90,"n_iterations":14,"time":11036,"converged":true,"accuracy":1.6e-10,"fermi":12.7801,"total_energy":-55.35134593},{"ecutrho":260,"k_density":0.16666666666666666,"ecutwfc":90,"n_iterations":12,"time":38016,"converged":true,"accuracy":3.0e-10,"fermi":12.6907,"total_energy":-55.350368445},{"ecutrho":260,"k_density":0.125,"ecutwfc":90,"n_iterations":13,"time":89050,"converged":true,"accuracy":8.0e-11,"fermi":12.734,"total_energy":-55.350946715},{"ecutrho":300,"k_density":0.5,"ecutwfc":90,"n_iterations":22,"time":2048,"converged":true,"accuracy":2.8e-10,"fermi":12.48,"total_energy":-55.344569805},{"ecutrho":300,"k_density":0.25,"ecutwfc":90,"n_iterations":14,"time":12071,"converged":true,"accuracy":4.5e-11,"fermi":12.7801,"total_energy":-55.35134394},{"ecutrho":300,"k_density":0.16666666666666666,"ecutwfc":90,"n_iterations":12,"time":41014,"converged":true,"accuracy":3.0e-10,"fermi":12.6906,"total_energy":-55.350366365},{"ecutrho":300,"k_density":0.125,"ecutwfc":90,"n_iterations":13,"time":97106,"converged":true,"accuracy":8.6e-11,"fermi":12.7339,"total_energy":-55.350944595},{"ecutrho":340,"k_density":0.1,"ecutwfc":90,"n_iterations":12,"time":181172,"converged":true,"accuracy":1.4e-10,"fermi":12.7104,"total_energy":-55.350876495},{"ecutrho":340,"k_density":0.25,"ecutwfc":90,"n_iterations":14,"time":12062,"converged":true,"accuracy":1.5e-11,"fermi":12.7801,"total_energy":-55.351349785},{"ecutrho":340,"k_density":0.16666666666666666,"ecutwfc":90,"n_iterations":12,"time":41029,"converged":true,"accuracy":2.9e-10,"fermi":12.6906,"total_energy":-55.35037217},{"ecutrho":380,"k_density":0.1,"ecutwfc":90,"n_iterations":12,"time":183102,"converged":true,"accuracy":1.4e-10,"fermi":12.7104,"total_energy":-55.350874725},{"ecutrho":380,"k_density":0.5,"ecutwfc":90,"n_iterations":24,"time":2079,"converged":true,"accuracy":6.4e-10,"fermi":12.48,"total_energy":-55.34457392},{"ecutrho":380,"k_density":0.25,"ecutwfc":90,"n_iterations":14,"time":12087,"converged":true,"accuracy":5.7e-12,"fermi":12.7801,"total_energy":-55.351347955},{"ecutrho":380,"k_density":0.16666666666666666,"ecutwfc":90,"n_iterations":12,"time":41054,"converged":true,"accuracy":3.1e-10,"fermi":12.6907,"total_energy":-55.350370405},{"ecutrho":140,"k_density":0.5,"ecutwfc":95,"n_iterations":17,"time":1073,"converged":true,"accuracy":2.6e-10,"fermi":12.4808,"total_energy":-55.344796295},{"ecutrho":140,"k_density":0.25,"ecutwfc":95,"n_iterations":15,"time":10082,"converged":true,"accuracy":1.1e-10,"fermi":12.781,"total_energy":-55.35156661},{"ecutrho":140,"k_density":0.16666666666666666,"ecutwfc":95,"n_iterations":12,"time":31167,"converged":true,"accuracy":3.5e-11,"fermi":12.6915,"total_energy":-55.350589965},{"ecutrho":140,"k_density":0.125,"ecutwfc":95,"n_iterations":13,"time":78146,"converged":true,"accuracy":4.0e-10,"fermi":12.7348,"total_energy":-55.35116838},{"ecutrho":180,"k_density":0.1,"ecutwfc":95,"n_iterations":12,"time":154108,"converged":true,"accuracy":1.7e-11,"fermi":12.7104,"total_energy":-55.3508339},{"ecutrho":180,"k_density":0.5,"ecutwfc":95,"n_iterations":18,"time":1080,"converged":true,"accuracy":2.3e-10,"fermi":12.48,"total_energy":-55.34453531},{"ecutrho":180,"k_density":0.25,"ecutwfc":95,"n_iterations":15,"time":10077,"converged":true,"accuracy":5.8e-10,"fermi":12.7802,"total_energy":-55.351306475},{"ecutrho":180,"k_density":0.16666666666666666,"ecutwfc":95,"n_iterations":12,"time":31125,"converged":true,"accuracy":3.6e-11,"fermi":12.6907,"total_energy":-55.350329595},{"ecutrho":180,"k_density":0.125,"ecutwfc":95,"n_iterations":13,"time":81015,"converged":true,"accuracy":4.0e-10,"fermi":12.7339,"total_energy":-55.35090807},{"ecutrho":220,"k_density":0.1,"ecutwfc":95,"n_iterations":12,"time":155096,"converged":true,"accuracy":1.9e-11,"fermi":12.7105,"total_energy":-55.35088759},{"ecutrho":220,"k_density":0.5,"ecutwfc":95,"n_iterations":15,"time":1057,"converged":true,"accuracy":8.8e-10,"fermi":12.4801,"total_energy":-55.34458796},{"ecutrho":220,"k_density":0.25,"ecutwfc":95,"n_iterations":15,"time":10116,"converged":true,"accuracy":1.8e-10,"fermi":12.7802,"total_energy":-55.35136045},{"ecutrho":220,"k_density":0.16666666666666666,"ecutwfc":95,"n_iterations":12,"time":31163,"converged":true,"accuracy":4.2e-11,"fermi":12.6908,"total_energy":-55.350383275},{"ecutrho":220,"k_density":0.125,"ecutwfc":95,"n_iterations":13,"time":82079,"converged":true,"accuracy":3.9e-10,"fermi":12.7341,"total_energy":-55.35096172},{"ecutrho":260,"k_density":0.1,"ecutwfc":95,"n_iterations":12,"time":170115,"converged":true,"accuracy":1.6e-11,"fermi":12.7104,"total_energy":-55.350886345},{"ecutrho":260,"k_density":0.5,"ecutwfc":95,"n_iterations":18,"time":1100,"converged":true,"accuracy":4.8e-10,"fermi":12.48,"total_energy":-55.34458546},{"ecutrho":260,"k_density":0.25,"ecutwfc":95,"n_iterations":15,"time":11125,"converged":true,"accuracy":3.9e-10,"fermi":12.7801,"total_energy":-55.35135958},{"ecutrho":260,"k_density":0.16666666666666666,"ecutwfc":95,"n_iterations":12,"time":35061,"converged":true,"accuracy":4.6e-11,"fermi":12.6906,"total_energy":-55.35038204},{"ecutrho":300,"k_density":0.1,"ecutwfc":95,"n_iterations":12,"time":183088,"converged":true,"accuracy":1.7e-11,"fermi":12.7103,"total_energy":-55.350884235},{"ecutrho":300,"k_density":0.5,"ecutwfc":95,"n_iterations":17,"time":1108,"converged":true,"accuracy":7.2e-10,"fermi":12.48,"total_energy":-55.344583035},{"ecutrho":300,"k_density":0.25,"ecutwfc":95,"n_iterations":19,"time":15132,"converged":true,"accuracy":2.0e-11,"fermi":12.7801,"total_energy":-55.35135756},{"ecutrho":300,"k_density":0.125,"ecutwfc":95,"n_iterations":12,"time":90101,"converged":true,"accuracy":9.7e-10,"fermi":12.7339,"total_energy":-55.350958225},{"ecutrho":340,"k_density":0.1,"ecutwfc":95,"n_iterations":12,"time":183182,"converged":true,"accuracy":1.9e-11,"fermi":12.7104,"total_energy":-55.35089004},{"ecutrho":340,"k_density":0.5,"ecutwfc":95,"n_iterations":19,"time":2024,"converged":true,"accuracy":3.4e-11,"fermi":12.48,"total_energy":-55.344588775},{"ecutrho":340,"k_density":0.25,"ecutwfc":95,"n_iterations":19,"time":16050,"converged":true,"accuracy":1.0e-10,"fermi":12.7801,"total_energy":-55.351363405},{"ecutrho":340,"k_density":0.16666666666666666,"ecutwfc":95,"n_iterations":12,"time":38044,"converged":true,"accuracy":4.1e-11,"fermi":12.6906,"total_energy":-55.350385735},{"ecutrho":340,"k_density":0.125,"ecutwfc":95,"n_iterations":12,"time":90130,"converged":true,"accuracy":9.7e-10,"fermi":12.7339,"total_energy":-55.35096402},{"ecutrho":380,"k_density":0.5,"ecutwfc":95,"n_iterations":18,"time":2021,"converged":true,"accuracy":7.8e-10,"fermi":12.4799,"total_energy":-55.34458716},{"ecutrho":380,"k_density":0.25,"ecutwfc":95,"n_iterations":18,"time":14135,"converged":true,"accuracy":5.1e-10,"fermi":12.7801,"total_energy":-55.35136159},{"ecutrho":380,"k_density":0.16666666666666666,"ecutwfc":95,"n_iterations":12,"time":38097,"converged":true,"accuracy":4.8e-11,"fermi":12.6906,"total_energy":-55.350383985},{"ecutrho":380,"k_density":0.125,"ecutwfc":95,"n_iterations":12,"time":91133,"converged":true,"accuracy":9.5e-10,"fermi":12.7339,"total_energy":-55.350962285}]